Workbook

Sheet Dashboard
A1: Movie Industry ROI Analysis
A35: Analysis of 7,669 movies (5,000+ with valid budget and revenue data)
A36: Period: 1980-2020
A37: All revenues adjusted to 2023 dollars using CPI

Sheet Analysis
A2: Valid movie | B2: Yes
A4: Row Labels | B4: Average of Gross relative to budget
A5: G | B5: 3.5504056
A6: PG | B6: 3.1217287
A7: PG-13 | B7: 3.0216556
A8: R | B8: 2.40136
A9: NC-17 | B9: 1.5843237
A10: Grand Total | B10: 2.864802
A22: Valid movie | B22: Yes
A24: Row Labels | B24: Average of Gross relative to budget
A25: 8-9 | B25: 5.9867212
A26: 9-10 | B26: 4.9275759
A27: 7-8 | B27: 3.7524221
A28: 6-7 | B28: 2.5834207
A29: 5-6 | B29: 1.9381276
A30: 4-5 | B30: 1.7977551
A31: 3-4 | B31: 1.2591825
A32: 1-2 | B32: 1.1066367
A33: 2-3 | B33: 0.93170756
A34: Grand Total | B34: 2.8661203
A43: Valid movie | B43: Yes
A45: Row Labels | B45: Average of Gross relative to budget
A46: Family | B46: 10.143436
A47: Horror | B47: 4.2219441
A48: Mystery | B48: 3.6982681
A49: Animation | B49: 3.6833103
A50: Thriller | B50: 3.3342712
A51: Adventure | B51: 2.8997264
A52: Action | B52: 2.8727601
A53: Drama | B53: 2.5972081
A54: Comedy | B54: 2.5948028
A55: Biography | B55: 2.4134502
A56: Fantasy | B56: 2.3279211
A57: Crime | B57: 2.218839
... A61: Grand Total | B61: 2.8661203

Sheet Raw Movie Data
A1: name | B1: rating | C1: genre | D1: year | E1: released | F1: score | G1: votes | H1: director | I1: writer | J1: star | K1: country | L1: budget | M1: gross | N1: company | O1: runtime
A2: The Shining | B2: R | C2: Drama | D2: 1980 | E2: June 13, 1980 (United States) | F2: 8.4 | G2: 927000 | H2: Stanley Kubrick | I2: Stephen King | J2: Jack Nicholson | K2: United Kingdom | L2: 19000000 | M2: 46998772 | N2: Warner Bros. | O2: 146
A3: The Blue Lagoon | B3: R | C3: Adventure | D3: 1980 | E3: July 2, 1980 (United States) | F3: 5.8 | G3: 65000 | H3: Randal Kleiser | I3: Henry De Vere Stacpoole | J3: Brooke Shields | K3: United States | L3: 4500000 | M3: 58853106 | N3: Columbia Pictures | O3: 104
A4: Star Wars: Episode V - The Empire Strikes Back | B4: PG | C4: Action | D4: 1980 | E4: June 20, 1980 (United States) | F4: 8.7 | G4: 1200000 | H4: Irvin Kershner | I4: Leigh Brackett | J4: Mark Hamill | K4: United States | L4: 18000000 | M4: 538375067 | N4: Lucasfilm | O4: 124
A5: Airplane! | B5: PG | C5: Comedy | D5: 1980 | E5: July 2, 1980 (United States) | F5: 7.7 | G5: 221000 | H5: Jim Abrahams | I5: Jim Abrahams | J5: Robert Hays | K5: United States | L5: 3500000 | M5: 83453539 | N5: Paramount Pictures | O5: 88
A6: Caddyshack | B6: R | C6: Comedy | D6: 1980 | E6: July 25, 1980 (United States) | F6: 7.3 | G6: 108000 | H6: Harold Ramis | I6: Brian Doyle-Murray | J6: Chevy Chase | K6: United States | L6: 6000000 | M6: 39846344 | N6: Orion Pictures | O6: 98
A7: Friday the 13th | B7: R | C7: Horror | D7: 1980 | E7: May 9, 1980 (United States) | F7: 6.4 | G7: 123000 | H7: Sean S. Cunningham | I7: Victor Miller | J7: Betsy Palmer | K7: United States | L7: 550000 | M7: 39754601 | N7: Paramount Pictures | O7: 95
A8: The Blues Brothers | B8: R | C8: Action | D8: 1980 | E8: June 20, 1980 (United States) | F8: 7.9 | G8: 188000 | H8: John Landis | I8: Dan Aykroyd | J8: John Belushi | K8: United States | L8: 27000000 | M8: 115229890 | N8: Universal Pictures | O8: 133
A9: Raging Bull | B9: R | C9: Biography | D9: 1980 | E9: December 19, 1980 (United States) | F9: 8.2 | G9: 330000 | H9: Martin Scorsese | I9: Jake LaMotta | J9: Robert De Niro | K9: United States | L9: 18000000 | M9: 23402427 | N9: Chartoff-Winkler Productions | O9: 129
A10: Superman II | B10: PG | C10: Action | D10: 1980 | E10: June 19, 1981 (United States) | F10: 6.8 | G10: 101000 | H10: Richard Lester | I10: Jerry Siegel | J10: Gene Hackman | K10: United States | L10: 54000000 | M10: 108185706 | N10: Dovemead Films | O10: 127
A11: The Long Riders | B11: R | C11: Biography | D11: 1980 | E11: May 16, 1980 (United States) | F11: 7 | G11: 10000 | H11: Walter Hill | I11: Bill Bryden | J11: David Carradine | K11: United States | L11: 10000000 | M11: 15795189 | N11: United Artists | O11: 100
A12: Any Which Way You Can | B12: PG | C12: Action | D12: 1980 | E12: December 17, 1980 (United States) | F12: 6.1 | G12: 18000 | H12: Buddy Van Horn | I12: Stanford Sherman | J12: Clint Eastwood | K12: United States | L12: 15000000 | M12: 70687344 | N12: The Malpaso Company | O12: 116
A13: The Gods Must Be Crazy | B13: PG | C13: Adventure | D13: 1980 | E13: October 26, 1984 (United States) | F13: 7.3 | G13: 54000 | H13: Jamie Uys | I13: Jamie Uys | J13: N!xau | K13: South Africa | L13: 5000000 | M13: 30031783 | N13: C.A.T. Films | O13: 109
... A17: Somewhere in Time | B17: PG | C17: Drama | D17: 1980 | E17: October 3, 1980 (United States) | F17: 7.2 | G17: 27000 | H17: Jeannot Szwarc | I17: Richard Matheson | J17: Christopher Reeve | K17: United States | L17: 5100000 | M17: 9709597 | N17: Rastar Pictures | O17: 103
A18: Fame | B18: R | C18: Drama | D18: 1980 | E18: May 16, 1980 (United States) | F18: 6.6 | G18: 21000 | H18: Alan Parker | I18: Christopher Gore | J18: Eddie Barth | K18: United States | M18: 21202829 | N18: Metro-Goldwyn-Mayer (MGM) | O18: 134
A19: 9 to 5 | B19: PG | C19: Comedy | D19: 1980 | E19: December 19, 1980 (United States) | F19: 6.9 | G19: 29000 | H19: Colin Higgins | I19: Patricia Resnick | J19: Jane Fonda | K19: United States | L19: 10000000 | M19: 103300686 | N19: IPC Films | O19: 109
A20: The Fog | B20: R | C20: Horror | D20: 1980 | E20: February 8, 1980 (United States) | F20: 6.8 | G20: 66000 | H20: John Carpenter | I20: John Carpenter | J20: Adrienne Barbeau | K20: United States | L20: 1000000 | M20: 21448782 | N20: AVCO Embassy Pictures | O20: 89
A21: Stir Crazy | B21: R | C21: Comedy | D21: 1980 | E21: December 12, 1980 (United States) | F21: 6.8 | G21: 26000 | H21: Sidney Poitier | I21: Bruce Jay Friedman | J21: Gene Wilder | K21: United States | M21: 101300000 | N21: Columbia Pictures | O21: 111
A22: Cruising | B22: R | C22: Crime | D22: 1980 | E22: February 15, 1980 (United States) | F22: 6.5 | G22: 20000 | H22: William Friedkin | I22: William Friedkin | J22: Al Pacino | K22: West Germany | L22: 11000000 | M22: 19814523 | N22: Lorimar Film Entertainment | O22: 102
A23: Heaven's Gate | B23: R | C23: Adventure | D23: 1980 | E23: April 24, 1981 (United States) | F23: 6.8 | G23: 14000 | H23: Michael Cimino | I23: Michael Cimino | J23: Kris Kristofferson | K23: United States | L23: 44000000 | M23: 3484523 | N23: Partisan Productions | O23: 219
A24: The Final Countdown | B24: PG | C24: Action | D24: 1980 | E24: August 1, 1980 (United States) | F24: 6.7 | G24: 22000 | H24: Don Taylor | I24: Thomas Hunter | J24: Kirk Douglas | K24: United States | L24: 12000000 | M24: 16647800 | N24: Bryna Productions | O24: 103
A25: Xanadu | B25: PG | C25: Fantasy | D25: 1980 | E25: August 8, 1980 (United States) | F25: 5.3 | G25: 12000 | H25: Robert Greenwald | I25: Richard Christian Danus | J25: Olivia Newton-John | K25: United States | L25: 20000000 | M25: 22762571 | N25: Universal Pictures | O25: 96
A26: Urban Cowboy | B26: PG | C26: Drama | D26: 1980 | E26: June 6, 1980 (United States) | F26: 6.4 | G26: 14000 | H26: James Bridges | I26: Aaron Latham | J26: John Travolta | K26: United States | M26: 46918287 | N26: Paramount Pictures | O26: 132
A27: Altered States | B27: R | C27: Horror | D27: 1980 | E27: December 25, 1980 (United States) | F27: 6.9 | G27: 33000 | H27: Ken Russell | I27: Paddy Chayefsky | J27: William Hurt | K27: United States | M27: 19853892 | N27: Warner Bros. | O27: 102
A28: Little Darlings | B28: R | C28: Comedy | D28: 1980 | E28: March 21, 1980 (United States) | F28: 6.5 | G28: 5100 | H28: Ron Maxwell | I28: Kimi Peck | J28: Tatum O'Neal | K28: United States | M28: 34326249 | N28: Stephen Friedman/Kings Road Productions | O28: 96
A29: Raise the Titanic | B29: PG | C29: Action | D29: 1980 | E29: August 1, 1980 (United States) | F29: 5 | G29: 4100 | H29: Jerry Jameson | I29: Adam Kennedy | J29: Jason Robards | K29: United Kingdom | L29: 36000000 | N29: ITC Films | O29: 115
A30: Brubaker | B30: R | C30: Crime | D30: 1980 | E30: June 20, 1980 (United States) | F30: 7.2 | G30: 17000 | H30: Stuart Rosenberg | I30: W.D. Richter | J30: Robert Redford | K30: United States | L30: 9000000 | M30: 37121708 | N30: Twentieth Century Fox | O30: 131
A31: American Gigolo | B31: R | C31: Crime | D31: 1980 | E31: February 1, 1980 (United States) | F31: 6.2 | G31: 22000 | H31: Paul Schrader | I31: Paul Schrader | J31: Richard Gere | K31: United States | L31: 4800000 | M31: 22743674 | N31: Paramount Pictures | O31: 117
A32: My Bodyguard | B32: PG | C32: Comedy | D32: 1980 | E32: September 26, 1980 (United States) | F32: 7.1 | G32: 8900 | H32: Tony Bill | I32: Alan Ormsby | J32: Chris Makepeace | K32: United States | M32: 22482952 | N32: Twentieth Century Fox | O32: 102
A33: Prom Night | B33: R | C33: Horror | D33: 1980 | E33: July 18, 1980 (United States) | F33: 5.4 | G33: 16000 | H33: Paul Lynch | I33: William Gray | J33: Leslie Nielsen | K33: Canada | M33: 14796236 | N33: Guardian Trust Company | O33: 92
A34: Smokey and the Bandit II | B34: PG | C34: Action | D34: 1980 | E34: August 15, 1980 (United States) | F34: 5.3 | G34: 15000 | H34: Hal Needham | I34: Hal Needham | J34: Burt Reynolds | K34: United States | M34: 66132626 | N34: Universal Pictures | O34: 100
A35: Cattle Annie and Little Britches | B35: PG | C35: Drama | D35: 1980 | E35: April 24, 1981 (United States) | F35: 6.1 | G35: 604 | H35: Lamont Johnson | I35: David Eyre | J35: Scott Glenn | K35: United States | L35: 5100000 | M35: 534816 | N35: Cattle Annie Productions | O35: 97
A36: Seems Like Old Times | B36: PG | C36: Comedy | D36: 1980 | E36: December 19, 1980 (United States) | F36: 6.7 | G36: 9100 | H36: Jay Sandrich | I36: Neil Simon | J36: Goldie Hawn | K36: United States | M36: 43995918 | N36: Rastar Films | O36: 102
A37: Private Benjamin | B37: R | C37: Comedy | D37: 1980 | E37: October 10, 1980 (United States) | F37: 6.2 | G37: 24000 | H37: Howard Zieff | I37: Nancy Meyers | J37: Goldie Hawn | K37: United States | L37: 10000000 | M37: 69847348 | N37: Warner Bros. | O37: 109
A38: The Hollywood Knights | B38: R | C38: Comedy | D38: 1980 | E38: May 30, 1980 (United States) | F38: 6.3 | G38: 4300 | H38: Floyd Mutrux | I38: Floyd Mutrux | J38: Tony Danza | K38: United States | L38: 4000000 | M38: 10000000 | N38: PolyGram Filmed Entertainment | O38: 91
A39: Motel Hell | B39: R | C39: Comedy | D39: 1980 | E39: October 24, 1980 (United States) | F39: 6 | G39: 11000 | H39: Kevin Connor | I39: Robert Jaffe | J39: Rory Calhoun | K39: United States | L39: 3000000 | M39: 6342668 | N39: Camp Hill | O39: 101
A40: The Jazz Singer | B40: PG | C40: Drama | D40: 1980 | E40: December 19, 1980 (United States) | F40: 5.9 | G40: 4000 | H40: Richard Fleischer | I40: Samson Raphaelson | J40: Laurence Olivier | K40: United States | M40: 27118000 | N40: EMI Films | O40: 115
A41: Coal Miner's Daughter | B41: PG | C41: Biography | D41: 1980 | E41: March 7, 1980 (United States) | F41: 7.5 | G41: 17000 | H41: Michael Apted | I41: Thomas Rickman | J41: Sissy Spacek | K41: United States | M41: 67182787 | N41: Universal Pictures | O41: 124
A42: The Watcher in the Woods | B42: PG | C42: Family | D42: 1980 | E42: October 9, 1981 (United States) | F42: 6.3 | G42: 5700 | H42: John Hough | I42: Brian Clemens | J42: Bette Davis | K42: United States | M42: 5000000 | N42: Walt Disney Productions | O42: 84
A43: Breaker Morant | B43: PG | C43: Drama | D43: 1980 | E43: July 3, 1980 (Australia) | F43: 7.9 | G43: 13000 | H43: Bruce Beresford | I43: Jonathan Hardy | J43: Edward Woodward | K43: Australia | N43: The South Australian Film Corporation | O43: 107
A44: The Stunt Man | B44: R | C44: Action | D44: 1980 | E44: June 27, 1980 (United States) | F44: 7.1 | G44: 9000 | H44: Richard Rush | I44: Lawrence B. Marcus | J44: Peter O'Toole | K44: United States | L44: 3500000 | M44: 7063886 | N44: Melvin Simon Productions | O44: 131
A45: Where the Buffalo Roam | B45: R | C45: Biography | D45: 1980 | E45: April 25, 1980 (United States) | F45: 6.6 | G45: 11000 | H45: Art Linson | I45: Hunter S. Thompson | J45: Peter Boyle | K45: United States | M45: 6659377 | N45: Universal Pictures | O45: 99
A46: The Awakening | B46: R | C46: Horror | D46: 1980 | E46: October 31, 1980 (United States) | F46: 4.8 | G46: 2000 | H46: Mike Newell | I46: Allan Scott | J46: Charlton Heston | K46: United Kingdom | M46: 8415112 | N46: EMI Films | O46: 101
A47: Cheech and Chong's Next Movie | B47: R | C47: Comedy | D47: 1980 | E47: July 18, 1980 (United States) | F47: 6.1 | G47: 12000 | H47: Tommy Chong | I47: Tommy Chong | J47: Cheech Marin | K47: United States | M47: 41675194 | N47: Universal Pictures | O47: 99
A48: The Island | B48: R | C48: Action | D48: 1980 | E48: June 13, 1980 (United States) | F48: 5.3 | G48: 3900 | H48: Michael Ritchie | I48: Peter Benchley | J48: Michael Caine | K48: United States | L48: 22000000 | M48: 15716828 | N48: Universal Pictures | O48: 109
A49: The Boogey Man | B49: R | C49: Horror | D49: 1980 | E49: November 7, 1980 (United States) | F49: 4.6 | G49: 3900 | H49: Ulli Lommel | I49: Ulli Lommel | J49: Suzanna Love | K49: United States | L49: 300000 | N49: The Jerry Gross Organization | O49: 82
A50: The Nude Bomb | B50: PG | C50: Action | D50: 1980 | E50: May 9, 1980 (United States) | F50: 5.1 | G50: 3100 | H50: Clive Donner | I50: Mel Brooks | J50: Don Adams | K50: United States | L50: 15000000 | M50: 14662035 | N50: Universal Pictures | O50: 94
A51: Lion of the Desert | B51: PG | C51: Biography | D51: 1980 | E51: May 16, 1981 (Japan) | F51: 8.3 | G51: 15000 | H51: Moustapha Akkad | I51: David Butler | J51: Anthony Quinn | K51: Libya | L51: 35000000 | N51: Falcon International Productions | O51: 173
A52: Stardust Memories | B52: PG | C52: Comedy | D52: 1980 | E52: September 26, 1980 (United States) | F52: 7.3 | G52: 22000 | H52: Woody Allen | I52: Woody Allen | J52: Woody Allen | K52: United States | L52: 10000000 | M52: 10389003 | N52: Jack Rollins & Charles H. Joffe Productions | O52: 89
A53: Melvin and Howard | B53: R | C53: Comedy | D53: 1980 | E53: September 19, 1980 (United States) | F53: 6.8 | G53: 4500 | H53: Jonathan Demme | I53: Bo Goldman | J53: Paul Le Mat | K53: United States | L53: 7000000 | M53: 4309490 | N53: Universal Pictures | O53: 95
A54: Can't Stop the Music | B54: PG | C54: Biography | D54: 1980 | E54: June 20, 1980 (United States) | F54: 4.2 | G54: 3700 | H54: Nancy Walker | I54: Bronte Woodard | J54: Ray Simpson | K54: United States | L54: 20000000 | N54: EMI Films | O54: 124
A55: Bronco Billy | B55: PG | C55: Action | D55: 1980 | E55: June 11, 1980 (United States) | F55: 6.1 | G55: 11000 | H55: Clint Eastwood | I55: Dennis Hackin | J55: Clint Eastwood | K55: United States | L55: 6500000 | M55: 24265659 | N55: Warner Bros. | O55: 116
A56: City of Women | B56: R | C56: Comedy | D56: 1980 | E56: April 8, 1981 (United States) | F56: 7 | G56: 6700 | H56: Federico Fellini | I56: Federico Fellini | J56: Marcello Mastroianni | K56: Italy | M56: 12516 | N56: Opera Film Produzione | O56: 139
A57: The Private Eyes | B57: PG | C57: Comedy | D57: 1980 | E57: November 21, 1980 (United States) | F57: 6.7 | G57: 2900 | H57: Lang Elliott | I57: Tim Conway | J57: Tim Conway | K57: United States | N57: Tri Star Productions | O57: 91
A58: When Time Ran Out... | B58: PG | C58: Action | D58: 1980 | E58: March 28, 1980 (United States) | F58: 4.6 | G58: 2600 | H58: James Goldstone | I58: Gordon Thomas | J58: Paul Newman | K58: United States | L58: 20000000 | M58: 3763988 | N58: International Cinema | O58: 121
A59: Oh Heavenly Dog | B59: PG | C59: Comedy | D59: 1980 | E59: July 11, 1980 (United States) | F59: 5.4 | G59: 2400 | H59: Joe Camp | I59: Rod Browning | J59: Chevy Chase | K59: United States | L59: 6000000 | M59: 6216067 | N59: Mulberry Square Productions | O59: 103
A60: The Octagon | B60: R | C60: Action | D60: 1980 | E60: August 15, 1980 (United States) | F60: 5.1 | G60: 5200 | H60: Eric Karson | I60: Leigh Chapman | J60: Chuck Norris | K60: United States | L60: 4000000 | M60: 18971000 | N60: American Cinema Productions | O60: 103
A61: Hangar 18 | B61: PG | C61: Sci-Fi | D61: 1980 | E61: March 13, 1981 (Ireland) | F61: 5.3 | G61: 2400 | H61: James L. Conway | I61: Ken Pettus | J61: Darren McGavin | K61: United States | L61: 11000000 | N61: Sunn Classic Pictures | O61: 97
A62: Herbie Goes Bananas | B62: G | C62: Adventure | D62: 1980 | E62: June 25, 1980 (United States) | F62: 5 | G62: 5300 | H62: Vincent McEveety | I62: Don Tait | J62: Charles Martin Smith | K62: United States | M62: 18000000 | N62: Walt Disney Productions | O62: 100
A63: The Competition | B63: PG | C63: Drama | D63: 1980 | E63: December 3, 1980 (United States) | F63: 6.7 | G63: 1900 | H63: Joel Oliansky | I63: Joel Oliansky | J63: Richard Dreyfuss | K63: United States | M63: 14287755 | N63: Rastar Films | O63: 123
A64: It's My Turn | B64: R | C64: Comedy | D64: 1980 | E64: February 5, 1981 (Argentina) | F64: 5.5 | G64: 875 | H64: Claudia Weill | I64: Eleanor Bergstein | J64: Jill Clayburgh | K64: United States | N64: Rastar Films | O64: 91
A65: Honeysuckle Rose | B65: PG | C65: Drama | D65: 1980 | E65: July 18, 1980 (United States) | F65: 6.3 | G65: 1400 | H65: Jerry Schatzberg | I65: GÃ¶sta Stevens | J65: Willie Nelson | K65: United States | M65: 17815212 | N65: Major Studio Partners | O65: 119
A66: Resurrection | B66: PG | C66: Drama | D66: 1980 | E66: September 26, 1980 (United States) | F66: 7.3 | G66: 2800 | H66: Daniel Petrie | I66: Lewis John Carlino | J66: Ellen Burstyn | K66: United States | M66: 3910019 | N66: Universal Pictures | O66: 103
A67: Fatso | B67: PG | C67: Comedy | D67: 1980 | E67: February 1, 1980 (United States) | F67: 6.3 | G67: 2000 | H67: Anne Bancroft | I67: Anne Bancroft | J67: Dom DeLuise | K67: United States | M67: 7653061 | N67: Brooksfilms | O67: 93
A68: Moscow Does Not Believe in Tears | B68: PG | C68: Comedy | D68: 1980 | E68: February 11, 1980 (Soviet Union) | F68: 8.1 | G68: 12000 | H68: Vladimir Menshov | I68: Valentin Chernykh | J68: Vera Alentova | K68: Soviet Union | L68: 900000 | N68: Mosfilm | O68: 150
A69: The Fiendish Plot of Dr. Fu Manchu | B69: PG | C69: Comedy | D69: 1980 | E69: August 8, 1980 (United States) | F69: 5.1 | G69: 2000 | H69: Piers Haggard | I69: Rudy Dochtermann | J69: Peter Sellers | K69: United States | M69: 10697276 | N69: Braun Entertainment Group | O69: 100
A70: Serial | B70: R | C70: Comedy | D70: 1980 | E70: March 28, 1980 (United States) | F70: 6.6 | G70: 915 | H70: Bill Persky | I70: Cyra McFadden | J70: Martin Mull | K70: United States | M70: 9870727 | N70: Paramount Pictures | O70: 86
A71: Hero at Large | B71: PG | C71: Comedy | D71: 1980 | E71: February 8, 1980 (United States) | F71: 6 | G71: 1500 | H71: Martin Davidson | I71: AJ Carothers | J71: John Ritter | K71: United States | M71: 15934737 | N71: Kings Road Entertainment | O71: 98
A72: Wholly Moses! | B72: PG | C72: Comedy | D72: 1980 | E72: June 13, 1980 (United States) | F72: 4.7 | G72: 1800 | H72: Gary Weis | I72: Guy Thomas | J72: Dudley Moore | K72: United States | M72: 14155617 | N72: Columbia Pictures | O72: 103
A73: Bon Voyage, Charlie Brown (and Don't Come Back!!) | B73: G | C73: Animation | D73: 1980 | E73: May 30, 1980 (United States) | F73: 7.3 | G73: 2900 | H73: Bill Melendez | I73: Charles M. Schulz | J73: Scott Beach | K73: United States | M73: 2013193 | N73: Lee Mendelson Film Productions | O73: 75
A74: In God We Trust (or Gimme That Prime Time Religion) | B74: PG | C74: Comedy | D74: 1980 | E74: September 26, 1980 (United States) | F74: 5.5 | G74: 965 | H74: Marty Feldman | I74: Marty Feldman | J74: Marty Feldman | K74: United States | M74: 5215015 | N74: Universal Pictures | O74: 97
A75: Roadie | B75: PG | C75: Comedy | D75: 1980 | E75: June 13, 1980 (United States) | F75: 5.2 | G75: 1100 | H75: Alan Rudolph | I75: Big Boy Medlin | J75: Meat Loaf | K75: United States | M75: 4226370 | N75: Alive Enterprises | O75: 106
A76: Just Tell Me What You Want | B76: R | C76: Comedy | D76: 1980 | E76: January 18, 1980 (United States) | F76: 5.5 | G76: 585 | H76: Sidney Lumet | I76: Jay Presson Allen | J76: Ali MacGraw | K76: United States | M76: 2086905 | N76: Warner Bros. | O76: 112
A77: The Last Flight of Noah's Ark | B77: G | C77: Adventure | D77: 1980 | E77: June 25, 1980 (United States) | F77: 5.8 | G77: 1300 | H77: Charles Jarrott | I77: Ernest K. Gann | J77: Elliott Gould | K77: United States | L77: 6000000 | M77: 11000000 | N77: Walt Disney Productions | O77: 97
A78: Little Miss Marker | B78: PG | C78: Comedy | D78: 1980 | E78: March 21, 1980 (United States) | F78: 6.3 | G78: 1400 | H78: Walter Bernstein | I78: Damon Runyon | J78: Walter Matthau | K78: United States | M78: 6321392 | N78: Universal Pictures | O78: 103
A79: Willie & Phil | B79: R | C79: Comedy | D79: 1980 | E79: August 15, 1980 (United States) | F79: 5.9 | G79: 415 | H79: Paul Mazursky | I79: Jean Gruault | J79: Michael Ontkean | K79: United States | L79: 5500000 | M79: 4400000 | N79: Twentieth Century Fox | O79: 115
A80: Babylon | C80: Drama | D80: 1980 | E80: November 1980 (United Kingdom) | F80: 7.4 | G80: 1300 | H80: Franco Rosso | I80: Franco Rosso | J80: David N. Haynes | K80: United Kingdom | M80: 109749 | N80: Diversity Music | O80: 95
A81: Windwalker | B81: PG | C81: Adventure | D81: 1980 | E81: November 18, 1983 (Sweden) | F81: 6.9 | G81: 1000 | H81: Kieth Merrill | I81: Ray Goldrup | J81: Trevor Howard | K81: United States | L81: 3000000 | N81: Santa Fe International | O81: 108
A82: Phobia | B82: R | C82: Drama | D82: 1980 | E82: September 9, 1980 (United States) | F82: 4 | G82: 546 | H82: John Huston | I82: Gary Sherman | J82: Paul Michael Glaser | K82: Canada | L82: 5100000 | M82: 59167 | N82: Borough Park Productions | O82: 94
A83: Windows | B83: R | C83: Drama | D83: 1980 | E83: January 18, 1980 (United States) | F83: 4.8 | G83: 643 | H83: Gordon Willis | I83: Barry Siegel | J83: Talia Shire | K83: United States | M83: 2128395 | N83: Mike Lobell Productions | O83: 96
A84: Loving Couples | B84: PG | C84: Comedy | D84: 1980 | E84: October 24, 1980 (United States) | F84: 5.2 | G84: 351 | H84: Jack Smight | I84: Martin Donovan | J84: Shirley MacLaine | K84: United States | M84: 2806659 | N84: Time Life Films | O84: 97
A85: The King and the Mockingbird | B85: Not Rated | C85: Animation | D85: 1980 | E85: March 19, 1980 (France) | F85: 7.9 | G85: 4800 | H85: Paul Grimault | I85: Hans Christian Andersen | J85: Jean Martin | K85: France | M85: 167451 | N85: Les Films Paul Grimault | O85: 83
A86: Oh, God! Book II | B86: PG | C86: Comedy | D86: 1980 | E86: October 3, 1980 (United States) | F86: 5.2 | G86: 2100 | H86: Gilbert Cates | I86: Josh Greenfeld | J86: George Burns | K86: United States | M86: 14504277 | N86: Warner Bros. | O86: 94
A87: Those Lips, Those Eyes | B87: R | C87: Comedy | D87: 1980 | E87: August 15, 1980 (United States) | F87: 6.5 | G87: 269 | H87: Michael Pressman | I87: David Shaber | J87: Frank Langella | K87: United States | M87: 804713 | N87: Herb Jaffe | O87: 105
A88: La Cage aux Folles II | B88: R | C88: Comedy | D88: 1980 | E88: February 15, 1981 (United States) | F88: 5.8 | G88: 1900 | H88: Ã‰douard Molinaro | I88: Jean Poiret | J88: Michel Serrault | K88: France | M88: 6950125 | N88: Da.Ma. Cinematografica | O88: 102
A89: The Gong Show Movie | B89: R | C89: Comedy | D89: 1980 | E89: May 23, 1980 (United States) | F89: 4.3 | G89: 740 | H89: Chuck Barris | I89: Chuck Barris | J89: Chuck Barris | K89: United States | M89: 6621520 | N89: Chuck Barris Productions | O89: 89
A90: Gilda Live | B90: R | C90: Comedy | D90: 1980 | E90: March 28, 1980 (United States) | F90: 6.8 | G90: 599 | H90: Mike Nichols | I90: Anne Beatts | J90: Gilda Radner | K90: United States | M90: 2261507 | N90: Broadway Productions | O90: 96
A91: Why Would I Lie? | B91: PG | C91: Comedy | D91: 1980 | E91: August 8, 1980 (United States) | F91: 6.5 | G91: 211 | H91: Larry Peerce | I91: Hollis Hodges | J91: Treat Williams | K91: United States | M91: 1175855 | N91: Metro-Goldwyn-Mayer (MGM) | O91: 105
A92: First Family | B92: R | C92: Comedy | D92: 1980 | E92: December 25, 1980 (United States) | F92: 4.3 | G92: 593 | H92: Buck Henry | I92: Buck Henry | J92: Bob Newhart | K92: United States | M92: 15198912 | N92: F.F. Associates | O92: 97
A93: Mantis Fist Fighter | C93: Action | D93: 1980 | E93: July 9, 1982 (United States) | F93: 6.7 | G93: 230 | H93: Wing-Cho Yip | I93: Hsin-Yi Chang | J93: Ka-Yan Leung | K93: Hong Kong | N93: East Asia Film Company | O93: 89
A94: Indiana Jones and the Raiders of the Lost Ark | B94: PG | C94: Action | D94: 1981 | E94: June 12, 1981 (United States) | F94: 8.4 | G94: 905000 | H94: Steven Spielberg | I94: Lawrence Kasdan | J94: Harrison Ford | K94: United States | L94: 18000000 | M94: 389925971 | N94: Paramount Pictures | O94: 115
A95: Body Heat | B95: R | C95: Crime | D95: 1981 | E95: August 28, 1981 (United States) | F95: 7.4 | G95: 32000 | H95: Lawrence Kasdan | I95: Lawrence Kasdan | J95: William Hurt | K95: United States | M95: 24058838 | N95: The Ladd Company | O95: 113
A96: An American Werewolf in London | B96: R | C96: Comedy | D96: 1981 | E96: August 21, 1981 (United States) | F96: 7.5 | G96: 97000 | H96: John Landis | I96: John Landis | J96: David Naughton | K96: United Kingdom | L96: 10000000 | M96: 30669378 | N96: Polygram Pictures | O96: 97
A97: Escape from New York | B97: R | C97: Action | D97: 1981 | E97: July 10, 1981 (United States) | F97: 7.2 | G97: 131000 | H97: John Carpenter | I97: John Carpenter | J97: Kurt Russell | K97: United States | L97: 6000000 | M97: 25244626 | N97: AVCO Embassy Pictures | O97: 99
A98: The Evil Dead | B98: NC-17 | C98: Horror | D98: 1981 | E98: April 15, 1983 (United States) | F98: 7.5 | G98: 192000 | H98: Sam Raimi | I98: Sam Raimi | J98: Bruce Campbell | K98: United States | L98: 350000 | M98: 2956630 | N98: Renaissance Pictures | O98: 85
A99: Porky's | B99: R | C99: Comedy | D99: 1981 | E99: March 19, 1982 (United States) | F99: 6.2 | G99: 40000 | H99: Bob Clark | I99: Bob Clark | J99: Dan Monahan | K99: Canada | L99: 2500000 | M99: 111289673 | N99: Astral Bellevue PathÃ© | O99: 94
A100: Blow Out | B100: R | C100: Crime | D100: 1981 | E100: July 24, 1981 (United States) | F100: 7.4 | G100: 47000 | H100: Brian De Palma | I100: Brian De Palma | J100: John Travolta | K100: United States | L100: 18000000 | M100: 12000000 | N100: Filmways Pictures | O100: 108
A101: Clash of the Titans | B101: PG | C101: Action | D101: 1981 | E101: June 12, 1981 (United States) | F101: 6.9 | G101: 42000 | H101: Desmond Davis | I101: Beverley Cross | J101: Laurence Olivier | K101: United Kingdom | L101: 15000000 | M101: 41092328 | N101: Charles H. Schneer Productions | O101: 118
A102: Excalibur | B102: R | C102: Adventure | D102: 1981 | E102: April 10, 1981 (United States) | F102: 7.4 | G102: 59000 | H102: John Boorman | I102: Thomas Malory | J102: Nigel Terry | K102: United Kingdom | L102: 11000000 | M102: 34971136 | N102: Cinema '84 | O102: 140
A103: Mad Max 2 | B103: R | C103: Action | D103: 1981 | E103: May 21, 1982 (United States) | F103: 7.6 | G103: 170000 | H103: George Miller | I103: Terry Hayes | J103: Mel Gibson | K103: Australia | L103: 3000000 | M103: 23668369 | N103: Kennedy Miller Productions | O103: 96
...

Sheet Working Data
A1: name | B1: rating | C1: genre | D1: year | E1: released | F1: score | G1: votes | H1: director | I1: writer | J1: star | K1: country | L1: budget | M1: gross | N1: company | O1: runtime | P1: CPI of Release Year | Q1: Gross Revenue in 2023 Dollars | R1: Valid movie
A2: Disaster Movie | B2: PG-13 | C2: Comedy | D2: 2008 | E2: August 29, 2008 (United States) | F2: 1.9 | G2: 88000 | H2: Jason Friedberg | I2: Jason Friedberg | J2: Carmen Electra | K2: United States | L2: 20000000 | M2: 34816824 | N2: Lionsgate | O2: 87 | P2: =_xlfn.XLOOKUP(D2,Consumer_Price_Index!A:A,Consumer_Price_Index!B:B) -> 215.3 | Q2: =IF(ISNUMBER(M2), M2*(Consumer_Price_Index!$B$45/(_xlfn.XLOOKUP('Working Data'!D5308,Consumer_Price_Index!A:A,Consumer_Price_Index!B:B))), "Missing") -> 59902238 | R2: =IF(AND(ISNUMBER(L2), L2>0, ISNUMBER(M2), M2>0), "Yes", "No") -> Yes
A3: Superbabies: Baby Geniuses 2 | B3: PG | C3: Comedy | D3: 2004 | E3: August 27, 2004 (United States) | F3: 1.9 | G3: 30000 | H3: Bob Clark | I3: Robert Grasmere | J3: Jon Voight | K3: Germany | L3: 20000000 | M3: 9448644 | N3: ApolloMedia Distribution | O3: 88 | P3: =_xlfn.XLOOKUP(D3,Consumer_Price_Index!A:A,Consumer_Price_Index!B:B) -> 188.9 | Q3: =IF(ISNUMBER(M3), M3*(Consumer_Price_Index!$B$45/(_xlfn.XLOOKUP('Working Data'!D4596,Consumer_Price_Index!A:A,Consumer_Price_Index!B:B))), "Missing") -> 11995841 | R3: =IF(AND(ISNUMBER(L3), L3>0, ISNUMBER(M3), M3>0), "Yes", "No") -> Yes
A4: The Hottie & the Nottie | B4: PG-13 | C4: Comedy | D4: 2008 | E4: February 21, 2008 (Russia) | F4: 1.9 | G4: 36000 | H4: Tom Putnam | I4: Heidi Ferrer | J4: Paris Hilton | K4: United States | M4: 1596232 | N4: Purple Pictures | O4: 91 | P4: =_xlfn.XLOOKUP(D4,Consumer_Price_Index!A:A,Consumer_Price_Index!B:B) -> 215.3 | Q4: =IF(ISNUMBER(M4), M4*(Consumer_Price_Index!$B$45/(_xlfn.XLOOKUP('Working Data'!D5356,Consumer_Price_Index!A:A,Consumer_Price_Index!B:B))), "Missing") -> 2412559 | R4: =IF(AND(ISNUMBER(L4), L4>0, ISNUMBER(M4), M4>0), "Yes", "No") -> No
A5: From Justin to Kelly | B5: PG | C5: Comedy | D5: 2003 | E5: June 20, 2003 (United States) | F5: 2.1 | G5: 25000 | H5: Robert Iscove | I5: Kim Fuller | J5: Kelly Clarkson | K5: United States | L5: 12000000 | M5: 4928883 | N5: 19 Entertainment | O5: 81 | P5: =_xlfn.XLOOKUP(D5,Consumer_Price_Index!A:A,Consumer_Price_Index!B:B) -> 184 | Q5: =IF(ISNUMBER(M5), M5*(Consumer_Price_Index!$B$45/(_xlfn.XLOOKUP('Working Data'!D4414,Consumer_Price_Index!A:A,Consumer_Price_Index!B:B))), "Missing") -> 9854531.8 | R5: =IF(AND(ISNUMBER(L5), L5>0, ISNUMBER(M5), M5>0), "Yes", "No") -> Yes
A6: House of the Dead | B6: R | C6: Action | D6: 2003 | E6: October 10, 2003 (United States) | F6: 2.1 | G6: 36000 | H6: Uwe Boll | I6: Mark A. Altman | J6: Jonathan Cherry | K6: Germany | L6: 12000000 | M6: 13818181 | N6: Boll Kino Beteiligungs GmbH & Co. KG | O6: 90 | P6: =_xlfn.XLOOKUP(D6,Consumer_Price_Index!A:A,Consumer_Price_Index!B:B) -> 184 | Q6: =IF(ISNUMBER(M6), M6*(Consumer_Price_Index!$B$45/(_xlfn.XLOOKUP('Working Data'!D4344,Consumer_Price_Index!A:A,Consumer_Price_Index!B:B))), "Missing") -> 19555967 | R6: =IF(AND(ISNUMBER(L6), L6>0, ISNUMBER(M6), M6>0), "Yes", "No") -> Yes
A7: Leonard Part 6 | B7: PG | C7: Action | D7: 1987 | E7: December 18, 1987 (United States) | F7: 2.2 | G7: 7900 | H7: Paul Weiland | I7: Jonathan Reynolds | J7: Bill Cosby | K7: United States | L7: 24000000 | M7: 4615255 | N7: Columbia Pictures | O7: 85 | P7: =_xlfn.XLOOKUP(D7,Consumer_Price_Index!A:A,Consumer_Price_Index!B:B) -> 113.6 | Q7: =IF(ISNUMBER(M7), M7*(Consumer_Price_Index!$B$45/(_xlfn.XLOOKUP('Working Data'!D1191,Consumer_Price_Index!A:A,Consumer_Price_Index!B:B))), "Missing") -> 12830914 | R7: =IF(AND(ISNUMBER(L7), L7>0, ISNUMBER(M7), M7>0), "Yes", "No") -> Yes
A8: Son of the Mask | B8: PG | C8: Comedy | D8: 2005 | E8: February 18, 2005 (United States) | F8: 2.2 | G8: 53000 | H8: Lawrence Guterman | I8: Lance Khazei | J8: Jamie Kennedy | K8: United States | L8: 84000000 | M8: 59981548 | N8: New Line Cinema | O8: 94 | P8: =_xlfn.XLOOKUP(D8,Consumer_Price_Index!A:A,Consumer_Price_Index!B:B) -> 195.3 | Q8: =IF(ISNUMBER(M8), M8*(Consumer_Price_Index!$B$45/(_xlfn.XLOOKUP('Working Data'!D4725,Consumer_Price_Index!A:A,Consumer_Price_Index!B:B))), "Missing") -> 72785256 | R8: =IF(AND(ISNUMBER(L8), L8>0, ISNUMBER(M8), M8>0), "Yes", "No") -> Yes
A9: Student of the Year 2 | B9: Not Rated | C9: Action | D9: 2019 | E9: May 10, 2019 (United States) | F9: 2.2 | G9: 18000 | H9: Punit Malhotra | I9: Arshad Sayed | J9: Tiger Shroff | K9: India | M9: 1635907 | N9: Fox STAR Studios | O9: 146 | P9: =_xlfn.XLOOKUP(D9,Consumer_Price_Index!A:A,Consumer_Price_Index!B:B) -> 255.7 | Q9: =IF(ISNUMBER(M9), M9*(Consumer_Price_Index!$B$45/(_xlfn.XLOOKUP('Working Data'!D7597,Consumer_Price_Index!A:A,Consumer_Price_Index!B:B))), "Missing") -> 2285469.3 | R9: =IF(AND(ISNUMBER(L9), L9>0, ISNUMBER(M9), M9>0), "Yes", "No") -> No
A10: Who's Your Caddy? | B10: PG-13 | C10: Comedy | D10: 2007 | E10: July 27, 2007 (United States) | F10: 2.2 | G10: 15000 | H10: Don Michael Paul | I10: Don Michael Paul | J10: Big Boi | K10: United States | L10: 7000000 | M10: 5713425 | N10: Ascendant Pictures | O10: 93 | P10: =_xlfn.XLOOKUP(D10,Consumer_Price_Index!A:A,Consumer_Price_Index!B:B) -> 207.3 | Q10: =IF(ISNUMBER(M10), M10*(Consumer_Price_Index!$B$45/(_xlfn.XLOOKUP('Working Data'!D5196,Consumer_Price_Index!A:A,Consumer_Price_Index!B:B))), "Missing") -> 6933017.1 | R10: =IF(AND(ISNUMBER(L10), L10>0, ISNUMBER(M10), M10>0), "Yes", "No") -> Yes
A11: Glitter | B11: PG-13 | C11: Drama | D11: 2001 | E11: September 21, 2001 (United States) | F11: 2.3 | G11: 22000 | H11: Vondie Curtis-Hall | I11: Cheryl L. West | J11: Mariah Carey | K11: United States | L11: 22000000 | M11: 5271666 | N11: Twentieth Century Fox | O11: 104 | P11: =_xlfn.XLOOKUP(D11,Consumer_Price_Index!A:A,Consumer_Price_Index!B:B) -> 177.1 | Q11: =IF(ISNUMBER(M11), M11*(Consumer_Price_Index!$B$45/(_xlfn.XLOOKUP('Working Data'!D4024,Consumer_Price_Index!A:A,Consumer_Price_Index!B:B))), "Missing") -> 7967642 | R11: =IF(AND(ISNUMBER(L11), L11>0, ISNUMBER(M11), M11>0), "Yes", "No") -> Yes
A12: Alone in the Dark | B12: R | C12: Action | D12: 2005 | E12: January 28, 2005 (United States) | F12: 2.4 | G12: 42000 | H12: Uwe Boll | I12: Elan Mastai | J12: Christian Slater | K12: Canada | L12: 20000000 | M12: 12693645 | N12: AITD Productions | O12: 96 | P12: =_xlfn.XLOOKUP(D12,Consumer_Price_Index!A:A,Consumer_Price_Index!B:B) -> 195.3 | Q12: =IF(ISNUMBER(M12), M12*(Consumer_Price_Index!$B$45/(_xlfn.XLOOKUP('Working Data'!D4804,Consumer_Price_Index!A:A,Consumer_Price_Index!B:B))), "Missing") -> 19185286 | R12: =IF(AND(ISNUMBER(L12), L12>0, ISNUMBER(M12), M12>0), "Yes", "No") -> Yes
A13: Epic Movie | B13: PG-13 | C13: Adventure | D13: 2007 | E13: January 26, 2007 (United States) | F13: 2.4 | G13: 103000 | H13: Jason Friedberg | I13: Jason Friedberg | J13: Kal Penn | K13: United States | L13: 20000000 | M13: 87238158 | N13: New Regency Productions | O13: 86 | P13: =_xlfn.XLOOKUP(D13,Consumer_Price_Index!A:A,Consumer_Price_Index!B:B) -> 207.3 | Q13: =IF(ISNUMBER(M13), M13*(Consumer_Price_Index!$B$45/(_xlfn.XLOOKUP('Working Data'!D5110,Consumer_Price_Index!A:A,Consumer_Price_Index!B:B))), "Missing") -> 1.1075611e+08 | R13: =IF(AND(ISNUMBER(L13), L13>0, ISNUMBER(M13), M13>0), "Yes", "No") -> Yes
A14: Battlefield Earth | B14: PG-13 | C14: Action | D14: 2000 | E14: May 12, 2000 (United States) | F14: 2.5 | G14: 77000 | H14: Roger Christian | I14: Corey Mandell | J14: John Travolta | K14: United States | L14: 73000000 | M14: 29725663 | N14: Warner Bros. | O14: 118 | P14: =_xlfn.XLOOKUP(D14,Consumer_Price_Index!A:A,Consumer_Price_Index!B:B) -> 172.2 | Q14: =IF(ISNUMBER(M14), M14*(Consumer_Price_Index!$B$45/(_xlfn.XLOOKUP('Working Data'!D3686,Consumer_Price_Index!A:A,Consumer_Price_Index!B:B))), "Missing") -> 84176668 | R14: =IF(AND(ISNUMBER(L14), L14>0, ISNUMBER(M14), M14>0), "Yes", "No") -> Yes
A15: Dragonball Evolution | B15: PG | C15: Action | D15: 2009 | E15: April 10, 2009 (United States) | F15: 2.5 | G15: 71000 | H15: James Wong | I15: Ben Ramsey | J15: Justin Chatwin | K15: United States | L15: 30000000 | M15: 55720772 | N15: Twentieth Century Fox | O15: 85 | P15: =_xlfn.XLOOKUP(D15,Consumer_Price_Index!A:A,Consumer_Price_Index!B:B) -> 214.5 | Q15: =IF(ISNUMBER(M15), M15*(Consumer_Price_Index!$B$45/(_xlfn.XLOOKUP('Working Data'!D5528,Consumer_Price_Index!A:A,Consumer_Price_Index!B:B))), "Missing") -> 1.2465579e+08 | R15: =IF(AND(ISNUMBER(L15), L15>0, ISNUMBER(M15), M15>0), "Yes", "No") -> Yes
A16: Gigli | B16: R | C16: Comedy | D16: 2003 | E16: August 1, 2003 (United States) | F16: 2.5 | G16: 46000 | H16: Martin Brest | I16: Martin Brest | J16: Ben Affleck | K16: United States | L16: 54000000 | M16: 7266209 | N16: Revolution Studios | O16: 121 | P16: =_xlfn.XLOOKUP(D16,Consumer_Price_Index!A:A,Consumer_Price_Index!B:B) -> 184 | Q16: =IF(ISNUMBER(M16), M16*(Consumer_Price_Index!$B$45/(_xlfn.XLOOKUP('Working Data'!D4328,Consumer_Price_Index!A:A,Consumer_Price_Index!B:B))), "Missing") -> 22943149 | R16: =IF(AND(ISNUMBER(L16), L16>0, ISNUMBER(M16), M16>0), "Yes", "No") -> Yes
A17: Lawnmower Man 2: Beyond Cyberspace | B17: PG-13 | C17: Action | D17: 1996 | E17: January 12, 1996 (United States) | F17: 2.5 | G17: 9000 | H17: Farhad Mann | I17: Farhad Mann | J17: Patrick Bergin | K17: United States | L17: 15000000 | M17: 2409225 | N17: New Line Cinema | O17: 93 | P17: =_xlfn.XLOOKUP(D17,Consumer_Price_Index!A:A,Consumer_Price_Index!B:B) -> 156.9 | Q17: =IF(ISNUMBER(M17), M17*(Consumer_Price_Index!$B$45/(_xlfn.XLOOKUP('Working Data'!D2997,Consumer_Price_Index!A:A,Consumer_Price_Index!B:B))), "Missing") -> 3058711.9 | R17: =IF(AND(ISNUMBER(L17), L17>0, ISNUMBER(M17), M17>0), "Yes", "No") -> Yes
A18: The Garbage Pail Kids Movie | B18: PG | C18: Adventure | D18: 1987 | E18: August 22, 1987 (United States) | F18: 2.6 | G18: 7600 | H18: Rod Amateau | I18: Linda Palmer | J18: Anthony Newley | K18: United States | L18: 1000000 | M18: 1576615 | N18: Atlantic Entertainment Group | O18: 100 | P18: =_xlfn.XLOOKUP(D18,Consumer_Price_Index!A:A,Consumer_Price_Index!B:B) -> 113.6 | Q18: =IF(ISNUMBER(M18), M18*(Consumer_Price_Index!$B$45/(_xlfn.XLOOKUP('Working Data'!D1127,Consumer_Price_Index!A:A,Consumer_Price_Index!B:B))), "Missing") -> 3675551.6 | R18: =IF(AND(ISNUMBER(L18), L18>0, ISNUMBER(M18), M18>0), "Yes", "No") -> Yes
A19: Baby Geniuses | B19: PG | C19: Comedy | D19: 1999 | E19: March 12, 1999 (United States) | F19: 2.7 | G19: 26000 | H19: Bob Clark | I19: Steven Paul | J19: Kathleen Turner | K19: United States | L19: 12000000 | M19: 36450736 | N19: Crystal Sky Worldwide | O19: 97 | P19: =_xlfn.XLOOKUP(D19,Consumer_Price_Index!A:A,Consumer_Price_Index!B:B) -> 166.6 | Q19: =IF(ISNUMBER(M19), M19*(Consumer_Price_Index!$B$45/(_xlfn.XLOOKUP('Working Data'!D3561,Consumer_Price_Index!A:A,Consumer_Price_Index!B:B))), "Missing") -> 61737294 | R19: =IF(AND(ISNUMBER(L19), L19>0, ISNUMBER(M19), M19>0), "Yes", "No") -> Yes
A20: Ed | B20: PG | C20: Comedy | D20: 1996 | E20: March 15, 1996 (United States) | F20: 2.7 | G20: 8200 | H20: Bill CouturiÃ© | I20: Ken Richards | J20: Matt LeBlanc | K20: United States | L20: 24000000 | M20: 4422380 | N20: Longview Entertainment | O20: 94 | P20: =_xlfn.XLOOKUP(D20,Consumer_Price_Index!A:A,Consumer_Price_Index!B:B) -> 156.9 | Q20: =IF(ISNUMBER(M20), M20*(Consumer_Price_Index!$B$45/(_xlfn.XLOOKUP('Working Data'!D3044,Consumer_Price_Index!A:A,Consumer_Price_Index!B:B))), "Missing") -> 10309864 | R20: =IF(AND(ISNUMBER(L20), L20>0, ISNUMBER(M20), M20>0), "Yes", "No") -> Yes
A21: Inchon | B21: PG | C21: Drama | D21: 1981 | E21: September 17, 1982 (United States) | F21: 2.7 | G21: 659 | H21: Terence Young | I21: Robin Moore | J21: Laurence Olivier | K21: South Korea | L21: 46000000 | M21: 5200986 | N21: One Way Productions | O21: 140 | P21: =_xlfn.XLOOKUP(D21,Consumer_Price_Index!A:A,Consumer_Price_Index!B:B) -> 90.9 | Q21: =IF(ISNUMBER(M21), M21*(Consumer_Price_Index!$B$45/(_xlfn.XLOOKUP('Working Data'!D192,Consumer_Price_Index!A:A,Consumer_Price_Index!B:B))), "Missing") -> 9512247.5 | R21: =IF(AND(ISNUMBER(L21), L21>0, ISNUMBER(M21), M21>0), "Yes", "No") -> Yes
A22: It's Pat: the Movie | B22: PG-13 | C22: Comedy | D22: 1994 | E22: November 25, 1994 (Brazil) | F22: 2.7 | G22: 9500 | H22: Adam Bernstein | I22: Julia Sweeney | J22: Julia Sweeney | K22: United States | M22: 60822 | N22: Touchstone Pictures | O22: 77 | P22: =_xlfn.XLOOKUP(D22,Consumer_Price_Index!A:A,Consumer_Price_Index!B:B) -> 148.2 | Q22: =IF(ISNUMBER(M22), M22*(Consumer_Price_Index!$B$45/(_xlfn.XLOOKUP('Working Data'!D2592,Consumer_Price_Index!A:A,Consumer_Price_Index!B:B))), "Missing") -> 172234.79 | R22: =IF(AND(ISNUMBER(L22), L22>0, ISNUMBER(M22), M22>0), "Yes", "No") -> No
A23: Plump Fiction | B23: R | C23: Comedy | D23: 1997 | E23: May 23, 1997 (Poland) | F23: 2.7 | G23: 3600 | H23: Bob Koherr | I23: Bob Koherr | J23: Tommy Davidson | K23: United States | M23: 71145 | N23: Plump Fiction LLC | O23: 82 | P23: =_xlfn.XLOOKUP(D23,Consumer_Price_Index!A:A,Consumer_Price_Index!B:B) -> 160.5 | Q23: =IF(ISNUMBER(M23), M23*(Consumer_Price_Index!$B$45/(_xlfn.XLOOKUP('Working Data'!D3219,Consumer_Price_Index!A:A,Consumer_Price_Index!B:B))), "Missing") -> 86331.667 | R23: =IF(AND(ISNUMBER(L23), L23>0, ISNUMBER(M23), M23>0), "Yes", "No") -> No
A24: Date Movie | B24: PG-13 | C24: Comedy | D24: 2006 | E24: February 17, 2006 (United States) | F24: 2.8 | G24: 58000 | H24: Aaron Seltzer | I24: Jason Friedberg | J24: Alyson Hannigan | K24: United States | L24: 20000000 | M24: 85749034 | N24: New Regency Productions | O24: 83 | P24: =_xlfn.XLOOKUP(D24,Consumer_Price_Index!A:A,Consumer_Price_Index!B:B) -> 201.6 | Q24: =IF(ISNUMBER(M24), M24*(Consumer_Price_Index!$B$45/(_xlfn.XLOOKUP('Working Data'!D4990,Consumer_Price_Index!A:A,Consumer_Price_Index!B:B))), "Missing") -> 2.7075369e+08 | R24: =IF(AND(ISNUMBER(L24), L24>0, ISNUMBER(M24), M24>0), "Yes", "No") -> Yes
A25: Meet the Spartans | B25: PG-13 | C25: Comedy | D25: 2008 | E25: January 25, 2008 (United States) | F25: 2.8 | G25: 103000 | H25: Jason Friedberg | I25: Jason Friedberg | J25: Sean Maguire | K25: United States | L25: 30000000 | M25: 85897593 | N25: New Regency Productions | O25: 87 | P25: =_xlfn.XLOOKUP(D25,Consumer_Price_Index!A:A,Consumer_Price_Index!B:B) -> 215.3 | Q25: =IF(ISNUMBER(M25), M25*(Consumer_Price_Index!$B$45/(_xlfn.XLOOKUP('Working Data'!D5367,Consumer_Price_Index!A:A,Consumer_Price_Index!B:B))), "Missing") -> 1.9216591e+08 | R25: =IF(AND(ISNUMBER(L25), L25>0, ISNUMBER(M25), M25>0), "Yes", "No") -> Yes
A26: BloodRayne | B26: R | C26: Action | D26: 2005 | E26: January 6, 2006 (United States) | F26: 2.9 | G26: 34000 | H26: Uwe Boll | I26: Guinevere Turner | J26: Kristanna Loken | K26: Germany | L26: 25000000 | M26: 3650275 | N26: Boll Kino Beteiligungs GmbH & Co. KG | O26: 95 | P26: =_xlfn.XLOOKUP(D26,Consumer_Price_Index!A:A,Consumer_Price_Index!B:B) -> 195.3 | Q26: =IF(ISNUMBER(M26), M26*(Consumer_Price_Index!$B$45/(_xlfn.XLOOKUP('Working Data'!D4777,Consumer_Price_Index!A:A,Consumer_Price_Index!B:B))), "Missing") -> 7088838.7 | R26: =IF(AND(ISNUMBER(L26), L26>0, ISNUMBER(M26), M26>0), "Yes", "No") -> Yes
A27: Cool as Ice | B27: PG | C27: Comedy | D27: 1991 | E27: October 18, 1991 (United States) | F27: 2.9 | G27: 9100 | H27: David Kellogg | I27: David Stenn | J27: Vanilla Ice | K27: United States | L27: 6000000 | M27: 1193062 | N27: Alive Films | O27: 91 | P27: =_xlfn.XLOOKUP(D27,Consumer_Price_Index!A:A,Consumer_Price_Index!B:B) -> 136.2 | Q27: =IF(ISNUMBER(M27), M27*(Consumer_Price_Index!$B$45/(_xlfn.XLOOKUP('Working Data'!D1931,Consumer_Price_Index!A:A,Consumer_Price_Index!B:B))), "Missing") -> 3072916.2 | R27: =IF(AND(ISNUMBER(L27), L27>0, ISNUMBER(M27), M27>0), "Yes", "No") -> Yes
A28: Scream | B28: R | C28: Horror | D28: 1981 | E28: January 1, 1981 (United States) | F28: 2.9 | G28: 674 | H28: Byron Quisenberry | I28: Byron Quisenberry | J28: Pepper Martin | K28: United States | N28: Calendar International Pictures | O28: 82 | P28: =_xlfn.XLOOKUP(D28,Consumer_Price_Index!A:A,Consumer_Price_Index!B:B) -> 90.9 | Q28: =IF(ISNUMBER(M28), M28*(Consumer_Price_Index!$B$45/(_xlfn.XLOOKUP('Working Data'!D200,Consumer_Price_Index!A:A,Consumer_Price_Index!B:B))), "Missing") -> Missing | R28: =IF(AND(ISNUMBER(L28), L28>0, ISNUMBER(M28), M28>0), "Yes", "No") -> No
A29: Steel | B29: PG-13 | C29: Action | D29: 1997 | E29: August 15, 1997 (United States) | F29: 2.9 | G29: 12000 | H29: Kenneth Johnson | I29: Louise Simonson | J29: Shaquille O'Neal | K29: United States | L29: 16000000 | M29: 1710972 | N29: DC Entertainment | O29: 97 | P29: =_xlfn.XLOOKUP(D29,Consumer_Price_Index!A:A,Consumer_Price_Index!B:B) -> 160.5 | Q29: =IF(ISNUMBER(M29), M29*(Consumer_Price_Index!$B$45/(_xlfn.XLOOKUP('Working Data'!D3151,Consumer_Price_Index!A:A,Consumer_Price_Index!B:B))), "Missing") -> 3517767.7 | R29: =IF(AND(ISNUMBER(L29), L29>0, ISNUMBER(M29), M29>0), "Yes", "No") -> Yes
A30: 3 Ninjas: High Noon at Mega Mountain | B30: PG | C30: Action | D30: 1998 | E30: June 18, 1998 (Australia) | F30: 3 | G30: 11000 | H30: Sean McNamara | I30: Sean McNamara | J30: Loni Anderson | K30: United States | M30: 375805 | N30: Leeds/Ben-Ami Productions | O30: 93 | P30: =_xlfn.XLOOKUP(D30,Consumer_Price_Index!A:A,Consumer_Price_Index!B:B) -> 163 | Q30: =IF(ISNUMBER(M30), M30*(Consumer_Price_Index!$B$45/(_xlfn.XLOOKUP('Working Data'!D3401,Consumer_Price_Index!A:A,Consumer_Price_Index!B:B))), "Missing") -> 1102096.1 | R30: =IF(AND(ISNUMBER(L30), L30>0, ISNUMBER(M30), M30>0), "Yes", "No") -> No
A31: Bolero | B31: R | C31: Comedy | D31: 1984 | E31: August 31, 1984 (United States) | F31: 3 | G31: 5100 | H31: John Derek | I31: John Derek | J31: Bo Derek | K31: United States | L31: 7000000 | M31: 8914881 | N31: City Films | O31: 105 | P31: =_xlfn.XLOOKUP(D31,Consumer_Price_Index!A:A,Consumer_Price_Index!B:B) -> 103.9 | Q31: =IF(ISNUMBER(M31), M31*(Consumer_Price_Index!$B$45/(_xlfn.XLOOKUP('Working Data'!D530,Consumer_Price_Index!A:A,Consumer_Price_Index!B:B))), "Missing") -> 20783200 | R31: =IF(AND(ISNUMBER(L31), L31>0, ISNUMBER(M31), M31>0), "Yes", "No") -> Yes
A32: El Coyote | B32: R | C32: Action | D32: 2019 | E32: October 4, 2019 (United States) | F32: 3 | G32: 122 | H32: Jeffrey Nicholson | I32: Jeffrey Nicholson | J32: Michael Saquella | K32: United States | M32: 1101470 | N32: Cactus Blue Entertainment | O32: 93 | P32: =_xlfn.XLOOKUP(D32,Consumer_Price_Index!A:A,Consumer_Price_Index!B:B) -> 255.7 | Q32: =IF(ISNUMBER(M32), M32*(Consumer_Price_Index!$B$45/(_xlfn.XLOOKUP('Working Data'!D7642,Consumer_Price_Index!A:A,Consumer_Price_Index!B:B))), "Missing") -> 1664771.4 | R32: =IF(AND(ISNUMBER(L32), L32>0, ISNUMBER(M32), M32>0), "Yes", "No") -> No
A33: Jaws: the Revenge | B33: PG-13 | C33: Adventure | D33: 1987 | E33: July 17, 1987 (United States) | F33: 3 | G33: 42000 | H33: Joseph Sargent | I33: Peter Benchley | J33: Lorraine Gary | K33: United States | L33: 23000000 | M33: 51881013 | N33: Universal Pictures | O33: 89 | P33: =_xlfn.XLOOKUP(D33,Consumer_Price_Index!A:A,Consumer_Price_Index!B:B) -> 113.6 | Q33: =IF(ISNUMBER(M33), M33*(Consumer_Price_Index!$B$45/(_xlfn.XLOOKUP('Working Data'!D1069,Consumer_Price_Index!A:A,Consumer_Price_Index!B:B))), "Missing") -> 80942881 | R33: =IF(AND(ISNUMBER(L33), L33>0, ISNUMBER(M33), M33>0), "Yes", "No") -> Yes
A34: Kazaam | B34: PG | C34: Comedy | D34: 1996 | E34: July 17, 1996 (United States) | F34: 3 | G34: 23000 | H34: Paul Michael Glaser | I34: Paul Michael Glaser | J34: Shaquille O'Neal | K34: United States | L34: 20000000 | M34: 18937262 | N34: Interscope Communications | O34: 93 | P34: =_xlfn.XLOOKUP(D34,Consumer_Price_Index!A:A,Consumer_Price_Index!B:B) -> 156.9 | Q34: =IF(ISNUMBER(M34), M34*(Consumer_Price_Index!$B$45/(_xlfn.XLOOKUP('Working Data'!D2927,Consumer_Price_Index!A:A,Consumer_Price_Index!B:B))), "Missing") -> 53626243 | R34: =IF(AND(ISNUMBER(L34), L34>0, ISNUMBER(M34), M34>0), "Yes", "No") -> Yes
A35: The Lonely Lady | B35: R | C35: Drama | D35: 1983 | E35: September 30, 1983 (United States) | F35: 3 | G35: 938 | H35: Peter Sasdy | I35: Harold Robbins | J35: Pia Zadora | K35: United States | L35: 5000000 | M35: 1223200 | N35: Harold Robbins International Company | O35: 92 | P35: =_xlfn.XLOOKUP(D35,Consumer_Price_Index!A:A,Consumer_Price_Index!B:B) -> 99.6 | Q35: =IF(ISNUMBER(M35), M35*(Consumer_Price_Index!$B$45/(_xlfn.XLOOKUP('Working Data'!D429,Consumer_Price_Index!A:A,Consumer_Price_Index!B:B))), "Missing") -> 1457602.8 | R35: =IF(AND(ISNUMBER(L35), L35>0, ISNUMBER(M35), M35>0), "Yes", "No") -> Yes
A36: Bratz | B36: PG | C36: Comedy | D36: 2007 | E36: August 3, 2007 (United States) | F36: 3.1 | G36: 18000 | H36: Sean McNamara | I36: Susan Estelle Jansen | J36: Skyler Shaye | K36: United States | L36: 20000000 | M36: 26013153 | N36: Avi Arad & Associates | O36: 110 | P36: =_xlfn.XLOOKUP(D36,Consumer_Price_Index!A:A,Consumer_Price_Index!B:B) -> 207.3 | Q36: =IF(ISNUMBER(M36), M36*(Consumer_Price_Index!$B$45/(_xlfn.XLOOKUP('Working Data'!D5170,Consumer_Price_Index!A:A,Consumer_Price_Index!B:B))), "Missing") -> 87197005 | R36: =IF(AND(ISNUMBER(L36), L36>0, ISNUMBER(M36), M36>0), "Yes", "No") -> Yes
A37: Left Behind | B37: PG-13 | C37: Action | D37: 2014 | E37: October 3, 2014 (United States) | F37: 3.1 | G37: 38000 | H37: Vic Armstrong | I37: Paul Lalonde | J37: Nicolas Cage | K37: United States | L37: 16000000 | M37: 27405896 | N37: Stoney Lake Entertainment | O37: 110 | P37: =_xlfn.XLOOKUP(D37,Consumer_Price_Index!A:A,Consumer_Price_Index!B:B) -> 236.7 | Q37: =IF(ISNUMBER(M37), M37*(Consumer_Price_Index!$B$45/(_xlfn.XLOOKUP('Working Data'!D6595,Consumer_Price_Index!A:A,Consumer_Price_Index!B:B))), "Missing") -> 83841130 | R37: =IF(AND(ISNUMBER(L37), L37>0, ISNUMBER(M37), M37>0), "Yes", "No") -> Yes
A38: Martians Go Home | B38: PG-13 | C38: Comedy | D38: 1989 | E38: April 20, 1990 (United States) | F38: 3.1 | G38: 666 | H38: David Odell | I38: Fredric Brown | J38: Randy Quaid | K38: United States | M38: 129778 | N38: Edward R. Pressman Productions | O38: 89 | P38: =_xlfn.XLOOKUP(D38,Consumer_Price_Index!A:A,Consumer_Price_Index!B:B) -> 124 | Q38: =IF(ISNUMBER(M38), M38*(Consumer_Price_Index!$B$45/(_xlfn.XLOOKUP('Working Data'!D1634,Consumer_Price_Index!A:A,Consumer_Price_Index!B:B))), "Missing") -> 166849.61 | R38: =IF(AND(ISNUMBER(L38), L38>0, ISNUMBER(M38), M38>0), "Yes", "No") -> No
A39: More to Life | C39: Drama | D39: 2020 | E39: October 23, 2020 (United States) | F39: 3.1 | G39: 18 | H39: Joseph Ebanks | I39: Joseph Ebanks | J39: Shannon Bond | K39: United States | L39: 7000 | O39: 90 | P39: =_xlfn.XLOOKUP(D39,Consumer_Price_Index!A:A,Consumer_Price_Index!B:B) -> 258.8 | Q39: =IF(ISNUMBER(M39), M39*(Consumer_Price_Index!$B$45/(_xlfn.XLOOKUP('Working Data'!D7665,Consumer_Price_Index!A:A,Consumer_Price_Index!B:B))), "Missing") -> Missing | R39: =IF(AND(ISNUMBER(L39), L39>0, ISNUMBER(M39), M39>0), "Yes", "No") -> No
A40: Rollerball | B40: PG-13 | C40: Action | D40: 2002 | E40: February 8, 2002 (United States) | F40: 3.1 | G40: 26000 | H40: John McTiernan | I40: William Harrison | J40: Chris Klein | K40: United States | L40: 70000000 | M40: 25852764 | N40: Atlas Entertainment | O40: 98 | P40: =_xlfn.XLOOKUP(D40,Consumer_Price_Index!A:A,Consumer_Price_Index!B:B) -> 179.9 | Q40: =IF(ISNUMBER(M40), M40*(Consumer_Price_Index!$B$45/(_xlfn.XLOOKUP('Working Data'!D4168,Consumer_Price_Index!A:A,Consumer_Price_Index!B:B))), "Missing") -> 33808314 | R40: =IF(AND(ISNUMBER(L40), L40>0, ISNUMBER(M40), M40>0), "Yes", "No") -> Yes
A41: Barney's Great Adventure | B41: G | C41: Adventure | D41: 1998 | E41: April 3, 1998 (United States) | F41: 3.2 | G41: 3200 | H41: Steve Gomer | I41: Stephen White | J41: George Hearn | K41: Canada | L41: 15000000 | M41: 12218638 | N41: Polygram Filmed Entertainment | O41: 76 | P41: =_xlfn.XLOOKUP(D41,Consumer_Price_Index!A:A,Consumer_Price_Index!B:B) -> 163 | Q41: =IF(ISNUMBER(M41), M41*(Consumer_Price_Index!$B$45/(_xlfn.XLOOKUP('Working Data'!D3411,Consumer_Price_Index!A:A,Consumer_Price_Index!B:B))), "Missing") -> 27334941 | R41: =IF(AND(ISNUMBER(L41), L41>0, ISNUMBER(M41), M41>0), "Yes", "No") -> Yes
A42: Bucky Larson: Born to Be a Star | B42: R | C42: Comedy | D42: 2011 | E42: September 9, 2011 (United States) | F42: 3.2 | G42: 12000 | H42: Tom Brady | I42: Adam Sandler | J42: Nick Swardson | K42: United States | L42: 10000000 | M42: 2530394 | N42: Columbia Pictures | O42: 97 | P42: =_xlfn.XLOOKUP(D42,Consumer_Price_Index!A:A,Consumer_Price_Index!B:B) -> 224.9 | Q42: =IF(ISNUMBER(M42), M42*(Consumer_Price_Index!$B$45/(_xlfn.XLOOKUP('Working Data'!D5964,Consumer_Price_Index!A:A,Consumer_Price_Index!B:B))), "Missing") -> 3309060.3 | R42: =IF(AND(ISNUMBER(L42), L42>0, ISNUMBER(M42), M42>0), "Yes", "No") -> Yes
A43: Hardbodies 2 | B43: R | C43: Comedy | D43: 1986 | E43: September 12, 1986 (United States) | F43: 3.2 | G43: 1100 | H43: Mark Griffiths | I43: Mark Griffiths | J43: James Karen | K43: United States | M43: 78068 | N43: Chroma III Productions | O43: 88 | P43: =_xlfn.XLOOKUP(D43,Consumer_Price_Index!A:A,Consumer_Price_Index!B:B) -> 109.6 | Q43: =IF(ISNUMBER(M43), M43*(Consumer_Price_Index!$B$45/(_xlfn.XLOOKUP('Working Data'!D1002,Consumer_Price_Index!A:A,Consumer_Price_Index!B:B))), "Missing") -> 201076.24 | R43: =IF(AND(ISNUMBER(L43), L43>0, ISNUMBER(M43), M43>0), "Yes", "No") -> No
A44: Ringmaster | B44: R | C44: Comedy | D44: 1998 | E44: November 25, 1998 (United States) | F44: 3.2 | G44: 4900 | H44: Neil Abramson | I44: Jon Bernstein | J44: Jerry Springer | K44: United States | L44: 20000000 | M44: 9257103 | N44: Artisan Entertainment | O44: 90 | P44: =_xlfn.XLOOKUP(D44,Consumer_Price_Index!A:A,Consumer_Price_Index!B:B) -> 163 | Q44: =IF(ISNUMBER(M44), M44*(Consumer_Price_Index!$B$45/(_xlfn.XLOOKUP('Working Data'!D3425,Consumer_Price_Index!A:A,Consumer_Price_Index!B:B))), "Missing") -> 12285014 | R44: =IF(AND(ISNUMBER(L44), L44>0, ISNUMBER(M44), M44>0), "Yes", "No") -> Yes
A45: Shanghai Surprise | B45: PG-13 | C45: Adventure | D45: 1986 | E45: August 29, 1986 (United States) | F45: 3.2 | G45: 5000 | H45: Jim Goddard | I45: John Kohn | J45: Sean Penn | K45: United Kingdom | L45: 17000000 | M45: 2315683 | N45: HandMade Films | O45: 97 | P45: =_xlfn.XLOOKUP(D45,Consumer_Price_Index!A:A,Consumer_Price_Index!B:B) -> 109.6 | Q45: =IF(ISNUMBER(M45), M45*(Consumer_Price_Index!$B$45/(_xlfn.XLOOKUP('Working Data'!D993,Consumer_Price_Index!A:A,Consumer_Price_Index!B:B))), "Missing") -> 3735249.4 | R45: =IF(AND(ISNUMBER(L45), L45>0, ISNUMBER(M45), M45>0), "Yes", "No") -> Yes
A46: Slender Man | B46: PG-13 | C46: Horror | D46: 2018 | E46: August 10, 2018 (United States) | F46: 3.2 | G46: 30000 | H46: Sylvain White | I46: David Birke | J46: Joey King | K46: United States | L46: 10000000 | M46: 51738549 | N46: Screen Gems | O46: 93 | P46: =_xlfn.XLOOKUP(D46,Consumer_Price_Index!A:A,Consumer_Price_Index!B:B) -> 251.1 | Q46: =IF(ISNUMBER(M46), M46*(Consumer_Price_Index!$B$45/(_xlfn.XLOOKUP('Working Data'!D7347,Consumer_Price_Index!A:A,Consumer_Price_Index!B:B))), "Missing") -> 73222182 | R46: =IF(AND(ISNUMBER(L46), L46>0, ISNUMBER(M46), M46>0), "Yes", "No") -> Yes
A47: Jack and Jill | B47: PG | C47: Comedy | D47: 2011 | E47: November 11, 2011 (United States) | F47: 3.3 | G47: 80000 | H47: Dennis Dugan | I47: Ben Zook | J47: Adam Sandler | K47: United States | L47: 79000000 | M47: 149673788 | N47: Columbia Pictures | O47: 91 | P47: =_xlfn.XLOOKUP(D47,Consumer_Price_Index!A:A,Consumer_Price_Index!B:B) -> 224.9 | Q47: =IF(ISNUMBER(M47), M47*(Consumer_Price_Index!$B$45/(_xlfn.XLOOKUP('Working Data'!D5932,Consumer_Price_Index!A:A,Consumer_Price_Index!B:B))), "Missing") -> 2.1182352e+08 | R47: =IF(AND(ISNUMBER(L47), L47>0, ISNUMBER(M47), M47>0), "Yes", "No") -> Yes
A48: Texas Chainsaw Massacre: The Next Generation | B48: R | C48: Comedy | D48: 1994 | E48: January 1, 1994 (Germany) | F48: 3.3 | G48: 21000 | H48: Kim Henkel | I48: Kim Henkel | J48: RenÃ©e Zellweger | K48: United States | L48: 600000 | M48: 185898 | N48: Ultra Muchos Productions | O48: 87 | P48: =_xlfn.XLOOKUP(D48,Consumer_Price_Index!A:A,Consumer_Price_Index!B:B) -> 148.2 | Q48: =IF(ISNUMBER(M48), M48*(Consumer_Price_Index!$B$45/(_xlfn.XLOOKUP('Working Data'!D2492,Consumer_Price_Index!A:A,Consumer_Price_Index!B:B))), "Missing") -> 456799.36 | R48: =IF(AND(ISNUMBER(L48), L48>0, ISNUMBER(M48), M48>0), "Yes", "No") -> Yes
A49: The Emoji Movie | B49: PG | C49: Animation | D49: 2017 | E49: July 28, 2017 (United States) | F49: 3.3 | G49: 58000 | H49: Tony Leondis | I49: Tony Leondis | J49: T.J. Miller | K49: United States | L49: 50000000 | M49: 217776646 | N49: Columbia Pictures | O49: 86 | P49: =_xlfn.XLOOKUP(D49,Consumer_Price_Index!A:A,Consumer_Price_Index!B:B) -> 245.1 | Q49: =IF(ISNUMBER(M49), M49*(Consumer_Price_Index!$B$45/(_xlfn.XLOOKUP('Working Data'!D7147,Consumer_Price_Index!A:A,Consumer_Price_Index!B:B))), "Missing") -> 3.200991e+08 | R49: =IF(AND(ISNUMBER(L49), L49>0, ISNUMBER(M49), M49>0), "Yes", "No") -> Yes
A50: The Master of Disguise | B50: PG | C50: Adventure | D50: 2002 | E50: August 2, 2002 (United States) | F50: 3.3 | G50: 23000 | H50: Perry Andelin Blake | I50: Dana Carvey | J50: Dana Carvey | K50: United States | L50: 16000000 | M50: 43411001 | N50: Revolution Studios | O50: 80 | P50: =_xlfn.XLOOKUP(D50,Consumer_Price_Index!A:A,Consumer_Price_Index!B:B) -> 179.9 | Q50: =IF(ISNUMBER(M50), M50*(Consumer_Price_Index!$B$45/(_xlfn.XLOOKUP('Working Data'!D4139,Consumer_Price_Index!A:A,Consumer_Price_Index!B:B))), "Missing") -> 63807680 | R50: =IF(AND(ISNUMBER(L50), L50>0, ISNUMBER(M50), M50>0), "Yes", "No") -> Yes
A51: Barb Wire | B51: R | C51: Action | D51: 1996 | E51: May 3, 1996 (United States) | F51: 3.4 | G51: 26000 | H51: David Hogan | I51: Chris Warner | J51: Pamela Anderson | K51: United States | L51: 9000000 | M51: 3793614 | N51: Polygram Filmed Entertainment | O51: 98 | P51: =_xlfn.XLOOKUP(D51,Consumer_Price_Index!A:A,Consumer_Price_Index!B:B) -> 156.9 | Q51: =IF(ISNUMBER(M51), M51*(Consumer_Price_Index!$B$45/(_xlfn.XLOOKUP('Working Data'!D2918,Consumer_Price_Index!A:A,Consumer_Price_Index!B:B))), "Missing") -> 10742697 | R51: =IF(AND(ISNUMBER(L51), L51>0, ISNUMBER(M51), M51>0), "Yes", "No") -> Yes
A52: Catwoman | B52: PG-13 | C52: Action | D52: 2004 | E52: July 23, 2004 (United States) | F52: 3.4 | G52: 113000 | H52: Pitof | I52: Bob Kane | J52: Halle Berry | K52: United States | L52: 100000000 | M52: 82102379 | N52: Warner Bros. | O52: 104 | P52: =_xlfn.XLOOKUP(D52,Consumer_Price_Index!A:A,Consumer_Price_Index!B:B) -> 188.9 | Q52: =IF(ISNUMBER(M52), M52*(Consumer_Price_Index!$B$45/(_xlfn.XLOOKUP('Working Data'!D4523,Consumer_Price_Index!A:A,Consumer_Price_Index!B:B))), "Missing") -> 1.3243301e+08 | R52: =IF(AND(ISNUMBER(L52), L52>0, ISNUMBER(M52), M52>0), "Yes", "No") -> Yes
A53: Dumb and Dumberer: When Harry Met Lloyd | B53: PG-13 | C53: Comedy | D53: 2003 | E53: June 13, 2003 (United States) | F53: 3.4 | G53: 38000 | H53: Troy Miller | I53: Peter Farrelly | J53: Derek Richardson | K53: United States | L53: 19000000 | M53: 39267515 | N53: New Line Cinema | O53: 85 | P53: =_xlfn.XLOOKUP(D53,Consumer_Price_Index!A:A,Consumer_Price_Index!B:B) -> 184 | Q53: =IF(ISNUMBER(M53), M53*(Consumer_Price_Index!$B$45/(_xlfn.XLOOKUP('Working Data'!D4331,Consumer_Price_Index!A:A,Consumer_Price_Index!B:B))), "Missing") -> 47649589 | R53: =IF(AND(ISNUMBER(L53), L53>0, ISNUMBER(M53), M53>0), "Yes", "No") -> Yes
A54: Feardotcom | B54: R | C54: Crime | D54: 2002 | E54: August 30, 2002 (United States) | F54: 3.4 | G54: 20000 | H54: William Malone | I54: Moshe Diamant | J54: Stephen Dorff | K54: United Kingdom | L54: 40000000 | M54: 18902015 | N54: MDP Worldwide | O54: 101 | P54: =_xlfn.XLOOKUP(D54,Consumer_Price_Index!A:A,Consumer_Price_Index!B:B) -> 179.9 | Q54: =IF(ISNUMBER(M54), M54*(Consumer_Price_Index!$B$45/(_xlfn.XLOOKUP('Working Data'!D4212,Consumer_Price_Index!A:A,Consumer_Price_Index!B:B))), "Missing") -> 34570492 | R54: =IF(AND(ISNUMBER(L54), L54>0, ISNUMBER(M54), M54>0), "Yes", "No") -> Yes
A55: I Am Fear | B55: Not Rated | C55: Horror | D55: 2020 | E55: March 3, 2020 (United States) | F55: 3.4 | G55: 447 | H55: Kevin Shulman | I55: Kevin Shulman | J55: Kristina Klebe | K55: United States | M55: 13266 | N55: Roxwell Films | O55: 87 | P55: =_xlfn.XLOOKUP(D55,Consumer_Price_Index!A:A,Consumer_Price_Index!B:B) -> 258.8 | Q55: =IF(ISNUMBER(M55), M55*(Consumer_Price_Index!$B$45/(_xlfn.XLOOKUP('Working Data'!D7661,Consumer_Price_Index!A:A,Consumer_Price_Index!B:B))), "Missing") -> 22824.112 | R55: =IF(AND(ISNUMBER(L55), L55>0, ISNUMBER(M55), M55>0), "Yes", "No") -> No
A56: Mac and Me | B56: PG | C56: Adventure | D56: 1988 | E56: August 12, 1988 (United States) | F56: 3.4 | G56: 12000 | H56: Stewart Raffill | I56: Stewart Raffill | J56: Christine Ebersole | K56: United States | L56: 13000000 | M56: 6424112 | N56: Mac and Me Joint Venture | O56: 99 | P56: =_xlfn.XLOOKUP(D56,Consumer_Price_Index!A:A,Consumer_Price_Index!B:B) -> 118.3 | Q56: =IF(ISNUMBER(M56), M56*(Consumer_Price_Index!$B$45/(_xlfn.XLOOKUP('Working Data'!D1294,Consumer_Price_Index!A:A,Consumer_Price_Index!B:B))), "Missing") -> 19652881 | R56: =IF(AND(ISNUMBER(L56), L56>0, ISNUMBER(M56), M56>0), "Yes", "No") -> Yes
A57: Tarzan the Ape Man | B57: Approved | C57: Adventure | D57: 1981 | E57: July 24, 1981 (United States) | F57: 3.4 | G57: 5300 | H57: John Derek | I57: Tom Rowe | J57: Bo Derek | K57: United States | L57: 6500000 | M57: 36565280 | N57: Metro-Goldwyn-Mayer (MGM) | O57: 115 | P57: =_xlfn.XLOOKUP(D57,Consumer_Price_Index!A:A,Consumer_Price_Index!B:B) -> 90.9 | Q57: =IF(ISNUMBER(M57), M57*(Consumer_Price_Index!$B$45/(_xlfn.XLOOKUP('Working Data'!D122,Consumer_Price_Index!A:A,Consumer_Price_Index!B:B))), "Missing") -> 45456715 | R57: =IF(AND(ISNUMBER(L57), L57>0, ISNUMBER(M57), M57>0), "Yes", "No") -> Yes
A58: Teen Wolf Too | B58: PG | C58: Comedy | D58: 1987 | E58: November 20, 1987 (United States) | F58: 3.4 | G58: 11000 | H58: Christopher Leitch | I58: Jeph Loeb | J58: Jason Bateman | K58: United States | L58: 3000000 | M58: 7888703 | N58: Atlantic Entertainment Group | O58: 95 | P58: =_xlfn.XLOOKUP(D58,Consumer_Price_Index!A:A,Consumer_Price_Index!B:B) -> 113.6 | Q58: =IF(ISNUMBER(M58), M58*(Consumer_Price_Index!$B$45/(_xlfn.XLOOKUP('Working Data'!D1106,Consumer_Price_Index!A:A,Consumer_Price_Index!B:B))), "Missing") -> 20318578 | R58: =IF(AND(ISNUMBER(L58), L58>0, ISNUMBER(M58), M58>0), "Yes", "No") -> Yes
A59: Vampires Suck | B59: PG-13 | C59: Comedy | D59: 2010 | E59: August 18, 2010 (United States) | F59: 3.4 | G59: 47000 | H59: Jason Friedberg | I59: Jason Friedberg | J59: Jenn Proske | K59: United States | L59: 20000000 | M59: 80547866 | N59: New Regency Productions | O59: 82 | P59: =_xlfn.XLOOKUP(D59,Consumer_Price_Index!A:A,Consumer_Price_Index!B:B) -> 218.1 | Q59: =IF(ISNUMBER(M59), M59*(Consumer_Price_Index!$B$45/(_xlfn.XLOOKUP('Working Data'!D5787,Consumer_Price_Index!A:A,Consumer_Price_Index!B:B))), "Missing") -> 1.5642406e+08 | R59: =IF(AND(ISNUMBER(L59), L59>0, ISNUMBER(M59), M59>0), "Yes", "No") -> Yes
A60: Fifty Shades of Black | B60: R | C60: Comedy | D60: 2016 | E60: January 29, 2016 (United States) | F60: 3.5 | G60: 20000 | H60: Michael Tiddes | I60: Marlon Wayans | J60: Marlon Wayans | K60: United States | L60: 5000000 | M60: 22227514 | N60: Fermion Films | O60: 92 | P60: =_xlfn.XLOOKUP(D60,Consumer_Price_Index!A:A,Consumer_Price_Index!B:B) -> 240 | Q60: =IF(ISNUMBER(M60), M60*(Consumer_Price_Index!$B$45/(_xlfn.XLOOKUP('Working Data'!D7012,Consumer_Price_Index!A:A,Consumer_Price_Index!B:B))), "Missing") -> 27632491 | R60: =IF(AND(ISNUMBER(L60), L60>0, ISNUMBER(M60), M60>0), "Yes", "No") -> Yes
A61: High on the Hog | B61: R | C61: Action | D61: 2019 | E61: April 16, 2019 (United States) | F61: 3.5 | G61: 195 | H61: Tony Wash | I61: Andy Golub | J61: Sid Haig | K61: United States | L61: 1200000 | M61: 45696 | N61: Hicktown Entertainment | O61: 85 | P61: =_xlfn.XLOOKUP(D61,Consumer_Price_Index!A:A,Consumer_Price_Index!B:B) -> 255.7 | Q61: =IF(ISNUMBER(M61), M61*(Consumer_Price_Index!$B$45/(_xlfn.XLOOKUP('Working Data'!D7618,Consumer_Price_Index!A:A,Consumer_Price_Index!B:B))), "Missing") -> 54452.762 | R61: =IF(AND(ISNUMBER(L61), L61>0, ISNUMBER(M61), M61>0), "Yes", "No") -> Yes
A62: Homework | B62: R | C62: Comedy | D62: 1982 | E62: August 27, 1982 (United States) | F62: 3.5 | G62: 322 | H62: James Beshears | I62: Maurice Peterson | J62: Joan Collins | K62: United States | M62: 2914328 | N62: Jensen Farley Pictures | O62: 90 | P62: =_xlfn.XLOOKUP(D62,Consumer_Price_Index!A:A,Consumer_Price_Index!B:B) -> 96.5 | Q62: =IF(ISNUMBER(M62), M62*(Consumer_Price_Index!$B$45/(_xlfn.XLOOKUP('Working Data'!D308,Consumer_Price_Index!A:A,Consumer_Price_Index!B:B))), "Missing") -> 4546829.2 | R62: =IF(AND(ISNUMBER(L62), L62>0, ISNUMBER(M62), M62>0), "Yes", "No") -> No
A63: Lambada | B63: PG | C63: Drama | D63: 1990 | E63: March 16, 1990 (United States) | F63: 3.5 | G63: 979 | H63: Joel Silberg | I63: Joel Silberg | J63: J. Eddie Peck | K63: United States | M63: 4263112 | N63: Cannon Films | O63: 104 | P63: =_xlfn.XLOOKUP(D63,Consumer_Price_Index!A:A,Consumer_Price_Index!B:B) -> 130.7 | Q63: =IF(ISNUMBER(M63), M63*(Consumer_Price_Index!$B$45/(_xlfn.XLOOKUP('Working Data'!D1823,Consumer_Price_Index!A:A,Consumer_Price_Index!B:B))), "Missing") -> 7059620.8 | R63: =IF(AND(ISNUMBER(L63), L63>0, ISNUMBER(M63), M63>0), "Yes", "No") -> No
A64: Meatballs III: Summer Job | B64: R | C64: Comedy | D64: 1986 | E64: January 9, 1987 (United States) | F64: 3.5 | G64: 2200 | H64: George Mendeluk | I64: Janis Allen | J64: Sally Kellerman | K64: Canada | M64: 2147228 | N64: TMS Pictures | O64: 96 | P64: =_xlfn.XLOOKUP(D64,Consumer_Price_Index!A:A,Consumer_Price_Index!B:B) -> 109.6 | Q64: =IF(ISNUMBER(M64), M64*(Consumer_Price_Index!$B$45/(_xlfn.XLOOKUP('Working Data'!D983,Consumer_Price_Index!A:A,Consumer_Price_Index!B:B))), "Missing") -> 4293047.1 | R64: =IF(AND(ISNUMBER(L64), L64>0, ISNUMBER(M64), M64>0), "Yes", "No") -> No
A65: Police Academy: Mission to Moscow | B65: PG | C65: Comedy | D65: 1994 | E65: August 26, 1994 (United States) | F65: 3.5 | G65: 32000 | H65: Alan Metter | I65: Neal Israel | J65: G.W. Bailey | K65: United States | L65: 6200000 | M65: 126247 | N65: Warner Bros. | O65: 83 | P65: =_xlfn.XLOOKUP(D65,Consumer_Price_Index!A:A,Consumer_Price_Index!B:B) -> 148.2 | Q65: =IF(ISNUMBER(M65), M65*(Consumer_Price_Index!$B$45/(_xlfn.XLOOKUP('Working Data'!D2545,Consumer_Price_Index!A:A,Consumer_Price_Index!B:B))), "Missing") -> 171042.51 | R65: =IF(AND(ISNUMBER(L65), L65>0, ISNUMBER(M65), M65>0), "Yes", "No") -> Yes
A66: Scary Movie V | B66: PG-13 | C66: Comedy | D66: 2013 | E66: April 12, 2013 (United States) | F66: 3.5 | G66: 67000 | H66: Malcolm D. Lee | I66: David Zucker | J66: Simon Rex | K66: United States | L66: 20000000 | M66: 78378744 | N66: Dimension Films | O66: 86 | P66: =_xlfn.XLOOKUP(D66,Consumer_Price_Index!A:A,Consumer_Price_Index!B:B) -> 233 | Q66: =IF(ISNUMBER(M66), M66*(Consumer_Price_Index!$B$45/(_xlfn.XLOOKUP('Working Data'!D6333,Consumer_Price_Index!A:A,Consumer_Price_Index!B:B))), "Missing") -> 1.0401569e+08 | R66: =IF(AND(ISNUMBER(L66), L66>0, ISNUMBER(M66), M66>0), "Yes", "No") -> Yes
A67: Smokey and the Bandit Part 3 | B67: PG | C67: Action | D67: 1983 | E67: August 12, 1983 (United States) | F67: 3.5 | G67: 8200 | H67: Dick Lowry | I67: Stuart Birnbaum | J67: Jackie Gleason | K67: United States | M67: 5678950 | N67: Universal Pictures | O67: 85 | P67: =_xlfn.XLOOKUP(D67,Consumer_Price_Index!A:A,Consumer_Price_Index!B:B) -> 99.6 | Q67: =IF(ISNUMBER(M67), M67*(Consumer_Price_Index!$B$45/(_xlfn.XLOOKUP('Working Data'!D380,Consumer_Price_Index!A:A,Consumer_Price_Index!B:B))), "Missing") -> 10615804 | R67: =IF(AND(ISNUMBER(L67), L67>0, ISNUMBER(M67), M67>0), "Yes", "No") -> No
A68: Spice World | B68: PG | C68: Comedy | D68: 1997 | E68: January 23, 1998 (United States) | F68: 3.5 | G68: 34000 | H68: Bob Spiers | I68: Spice Girls | J68: Mel B | K68: United Kingdom | L68: 25000000 | M68: 29342592 | N68: Columbia Pictures | O68: 93 | P68: =_xlfn.XLOOKUP(D68,Consumer_Price_Index!A:A,Consumer_Price_Index!B:B) -> 160.5 | Q68: =IF(ISNUMBER(M68), M68*(Consumer_Price_Index!$B$45/(_xlfn.XLOOKUP('Working Data'!D3114,Consumer_Price_Index!A:A,Consumer_Price_Index!B:B))), "Missing") -> 45779251 | R68: =IF(AND(ISNUMBER(L68), L68>0, ISNUMBER(M68), M68>0), "Yes", "No") -> Yes
A69: Spy Kids 4-D: All the Time in the World | B69: PG | C69: Animation | D69: 2011 | E69: August 19, 2011 (United States) | F69: 3.5 | G69: 24000 | H69: Robert Rodriguez | I69: Robert Rodriguez | J69: Jessica Alba | K69: United States | L69: 27000000 | M69: 85564310 | N69: Dimension Films | O69: 89 | P69: =_xlfn.XLOOKUP(D69,Consumer_Price_Index!A:A,Consumer_Price_Index!B:B) -> 224.9 | Q69: =IF(ISNUMBER(M69), M69*(Consumer_Price_Index!$B$45/(_xlfn.XLOOKUP('Working Data'!D5991,Consumer_Price_Index!A:A,Consumer_Price_Index!B:B))), "Missing") -> 1.4492187e+08 | R69: =IF(AND(ISNUMBER(L69), L69>0, ISNUMBER(M69), M69>0), "Yes", "No") -> Yes
A70: American Ninja 3: Blood Hunt | B70: R | C70: Action | D70: 1989 | E70: February 24, 1989 (United States) | F70: 3.6 | G70: 5000 | H70: Cedric Sundstrom | I70: Avi Kleinberger | J70: David Bradley | K70: United States | M70: 902152 | N70: Breton Film Productions | O70: 89 | P70: =_xlfn.XLOOKUP(D70,Consumer_Price_Index!A:A,Consumer_Price_Index!B:B) -> 124 | Q70: =IF(ISNUMBER(M70), M70*(Consumer_Price_Index!$B$45/(_xlfn.XLOOKUP('Working Data'!D1613,Consumer_Price_Index!A:A,Consumer_Price_Index!B:B))), "Missing") -> 2759896.7 | R70: =IF(AND(ISNUMBER(L70), L70>0, ISNUMBER(M70), M70>0), "Yes", "No") -> No
A71: Carnosaur | B71: R | C71: Horror | D71: 1993 | E71: May 21, 1993 (United States) | F71: 3.6 | G71: 3700 | H71: Adam Simon | I71: John Brosnan | J71: Diane Ladd | K71: United States | L71: 850000 | M71: 1753979 | N71: New Horizons Picture | O71: 83 | P71: =_xlfn.XLOOKUP(D71,Consumer_Price_Index!A:A,Consumer_Price_Index!B:B) -> 144.5 | Q71: =IF(ISNUMBER(M71), M71*(Consumer_Price_Index!$B$45/(_xlfn.XLOOKUP('Working Data'!D2416,Consumer_Price_Index!A:A,Consumer_Price_Index!B:B))), "Missing") -> 4309979 | R71: =IF(AND(ISNUMBER(L71), L71>0, ISNUMBER(M71), M71>0), "Yes", "No") -> Yes
A72: Crossroads | B72: PG-13 | C72: Comedy | D72: 2002 | E72: February 15, 2002 (United States) | F72: 3.6 | G72: 39000 | H72: Tamra Davis | I72: Shonda Rhimes | J72: Britney Spears | K72: United States | L72: 12000000 | M72: 61141030 | N72: Fuzzy Bunny Films (I) | O72: 93 | P72: =_xlfn.XLOOKUP(D72,Consumer_Price_Index!A:A,Consumer_Price_Index!B:B) -> 179.9 | Q72: =IF(ISNUMBER(M72), M72*(Consumer_Price_Index!$B$45/(_xlfn.XLOOKUP('Working Data'!D4119,Consumer_Price_Index!A:A,Consumer_Price_Index!B:B))), "Missing") -> 74192242 | R72: =IF(AND(ISNUMBER(L72), L72>0, ISNUMBER(M72), M72>0), "Yes", "No") -> Yes
A73: Dirty Love | B73: R | C73: Comedy | D73: 2005 | E73: May 5, 2006 (Italy) | F73: 3.6 | G73: 6800 | H73: John Asher | I73: Jenny McCarthy | J73: Jenny McCarthy | K73: United States | M73: 36099 | N73: Big Screen Entertainment Group | O73: 91 | P73: =_xlfn.XLOOKUP(D73,Consumer_Price_Index!A:A,Consumer_Price_Index!B:B) -> 195.3 | Q73: =IF(ISNUMBER(M73), M73*(Consumer_Price_Index!$B$45/(_xlfn.XLOOKUP('Working Data'!D4841,Consumer_Price_Index!A:A,Consumer_Price_Index!B:B))), "Missing") -> 44877.051 | R73: =IF(AND(ISNUMBER(L73), L73>0, ISNUMBER(M73), M73>0), "Yes", "No") -> No
A74: I Know Who Killed Me | B74: R | C74: Crime | D74: 2007 | E74: July 27, 2007 (United States) | F74: 3.6 | G74: 26000 | H74: Chris Sivertson | I74: Jeff Hammond | J74: Lindsay Lohan | K74: United States | L74: 12000000 | M74: 9669758 | N74: 360 Pictures | O74: 105 | P74: =_xlfn.XLOOKUP(D74,Consumer_Price_Index!A:A,Consumer_Price_Index!B:B) -> 207.3 | Q74: =IF(ISNUMBER(M74), M74*(Consumer_Price_Index!$B$45/(_xlfn.XLOOKUP('Working Data'!D5201,Consumer_Price_Index!A:A,Consumer_Price_Index!B:B))), "Missing") -> 27382670 | R74: =IF(AND(ISNUMBER(L74), L74>0, ISNUMBER(M74), M74>0), "Yes", "No") -> Yes
A75: Kalank | B75: Not Rated | C75: Drama | D75: 2019 | E75: April 17, 2019 (United States) | F75: 3.6 | G75: 12000 | H75: Abhishek Varman | I75: Shibani Bathija | J75: Varun Dhawan | K75: India | M75: 17987034 | N75: Dharma Productions | O75: 166 | P75: =_xlfn.XLOOKUP(D75,Consumer_Price_Index!A:A,Consumer_Price_Index!B:B) -> 255.7 | Q75: =IF(ISNUMBER(M75), M75*(Consumer_Price_Index!$B$45/(_xlfn.XLOOKUP('Working Data'!D7587,Consumer_Price_Index!A:A,Consumer_Price_Index!B:B))), "Missing") -> 52749271 | R75: =IF(AND(ISNUMBER(L75), L75>0, ISNUMBER(M75), M75>0), "Yes", "No") -> No
A76: Swept Away | B76: R | C76: Comedy | D76: 2002 | E76: October 11, 2002 (United States) | F76: 3.6 | G76: 16000 | H76: Guy Ritchie | I76: Guy Ritchie | J76: Madonna | K76: United Kingdom | L76: 10000000 | M76: 1036520 | N76: Screen Gems | O76: 89 | P76: =_xlfn.XLOOKUP(D76,Consumer_Price_Index!A:A,Consumer_Price_Index!B:B) -> 179.9 | Q76: =IF(ISNUMBER(M76), M76*(Consumer_Price_Index!$B$45/(_xlfn.XLOOKUP('Working Data'!D4152,Consumer_Price_Index!A:A,Consumer_Price_Index!B:B))), "Missing") -> 2935201.2 | R76: =IF(AND(ISNUMBER(L76), L76>0, ISNUMBER(M76), M76>0), "Yes", "No") -> Yes
A77: Time Walker | B77: PG | C77: Horror | D77: 1982 | E77: November 19, 1982 (United States) | F77: 3.6 | G77: 1700 | H77: Tom Kennedy | I77: Jason Williams | J77: Ben Murphy | K77: United States | L77: 750000 | N77: Byzantine Productions | O77: 83 | P77: =_xlfn.XLOOKUP(D77,Consumer_Price_Index!A:A,Consumer_Price_Index!B:B) -> 96.5 | Q77: =IF(ISNUMBER(M77), M77*(Consumer_Price_Index!$B$45/(_xlfn.XLOOKUP('Working Data'!D268,Consumer_Price_Index!A:A,Consumer_Price_Index!B:B))), "Missing") -> Missing | R77: =IF(AND(ISNUMBER(L77), L77>0, ISNUMBER(M77), M77>0), "Yes", "No") -> No
A78: Aces: Iron Eagle III | B78: R | C78: Action | D78: 1992 | E78: June 12, 1992 (United States) | F78: 3.7 | G78: 2700 | H78: John Glen | I78: Kevin Alyn Elders | J78: Louis Gossett Jr. | K78: United Kingdom | M78: 2517600 | N78: Carolco Pictures | O78: 98 | P78: =_xlfn.XLOOKUP(D78,Consumer_Price_Index!A:A,Consumer_Price_Index!B:B) -> 140.3 | Q78: =IF(ISNUMBER(M78), M78*(Consumer_Price_Index!$B$45/(_xlfn.XLOOKUP('Working Data'!D2212,Consumer_Price_Index!A:A,Consumer_Price_Index!B:B))), "Missing") -> 9309620.4 | R78: =IF(AND(ISNUMBER(L78), L78>0, ISNUMBER(M78), M78>0), "Yes", "No") -> No
A79: Alien Predator | B79: R | C79: Drama | D79: 1986 | E79: February 6, 1987 (United States) | F79: 3.7 | G79: 922 | H79: Deran Sarafian | I79: Deran Sarafian | J79: Dennis Christopher | K79: United States | N79: Continental Motion Pictures | O79: 90 | P79: =_xlfn.XLOOKUP(D79,Consumer_Price_Index!A:A,Consumer_Price_Index!B:B) -> 109.6 | Q79: =IF(ISNUMBER(M79), M79*(Consumer_Price_Index!$B$45/(_xlfn.XLOOKUP('Working Data'!D1042,Consumer_Price_Index!A:A,Consumer_Price_Index!B:B))), "Missing") -> Missing | R79: =IF(AND(ISNUMBER(L79), L79>0, ISNUMBER(M79), M79>0), "Yes", "No") -> No
A80: Ballistic: Ecks vs. Sever | B80: R | C80: Action | D80: 2002 | E80: September 20, 2002 (United States) | F80: 3.7 | G80: 19000 | H80: Wych Kaosayananda | I80: Alan B. McElroy | J80: Antonio Banderas | K80: United States | L80: 70000000 | M80: 20154899 | N80: Franchise Pictures | O80: 91 | P80: =_xlfn.XLOOKUP(D80,Consumer_Price_Index!A:A,Consumer_Price_Index!B:B) -> 179.9 | Q80: =IF(ISNUMBER(M80), M80*(Consumer_Price_Index!$B$45/(_xlfn.XLOOKUP('Working Data'!D4231,Consumer_Price_Index!A:A,Consumer_Price_Index!B:B))), "Missing") -> 46986976 | R80: =IF(AND(ISNUMBER(L80), L80>0, ISNUMBER(M80), M80>0), "Yes", "No") -> Yes
A81: Body Rock | B81: PG-13 | C81: Drama | D81: 1984 | E81: September 28, 1984 (United States) | F81: 3.7 | G81: 446 | H81: Marcelo Epstein | I81: Desmond Nakano | J81: Lorenzo Lamas | K81: United States | M81: 1689501 | N81: New World Pictures | O81: 93 | P81: =_xlfn.XLOOKUP(D81,Consumer_Price_Index!A:A,Consumer_Price_Index!B:B) -> 103.9 | Q81: =IF(ISNUMBER(M81), M81*(Consumer_Price_Index!$B$45/(_xlfn.XLOOKUP('Working Data'!D615,Consumer_Price_Index!A:A,Consumer_Price_Index!B:B))), "Missing") -> 2391040.2 | R81: =IF(AND(ISNUMBER(L81), L81>0, ISNUMBER(M81), M81>0), "Yes", "No") -> No
A82: Dungeons & Dragons | B82: PG-13 | C82: Action | D82: 2000 | E82: December 8, 2000 (United States) | F82: 3.7 | G82: 32000 | H82: Courtney Solomon | I82: Topper Lilien | J82: Justin Whalin | K82: United States | L82: 45000000 | M82: 33978694 | N82: New Line Cinema | O82: 107 | P82: =_xlfn.XLOOKUP(D82,Consumer_Price_Index!A:A,Consumer_Price_Index!B:B) -> 172.2 | Q82: =IF(ISNUMBER(M82), M82*(Consumer_Price_Index!$B$45/(_xlfn.XLOOKUP('Working Data'!D3726,Consumer_Price_Index!A:A,Consumer_Price_Index!B:B))), "Missing") -> 71649191 | R82: =IF(AND(ISNUMBER(L82), L82>0, ISNUMBER(M82), M82>0), "Yes", "No") -> Yes
A83: Getting It on | B83: R | C83: Comedy | D83: 1983 | E83: August 1983 (United States) | F83: 3.7 | G83: 208 | H83: William Olsen | I83: William Olsen | J83: Martin Yost | K83: United States | L83: 220000 | M83: 975414 | N83: Seventh Avenue Films | O83: 96 | P83: =_xlfn.XLOOKUP(D83,Consumer_Price_Index!A:A,Consumer_Price_Index!B:B) -> 99.6 | Q83: =IF(ISNUMBER(M83), M83*(Consumer_Price_Index!$B$45/(_xlfn.XLOOKUP('Working Data'!D451,Consumer_Price_Index!A:A,Consumer_Price_Index!B:B))), "Missing") -> 1725950.3 | R83: =IF(AND(ISNUMBER(L83), L83>0, ISNUMBER(M83), M83>0), "Yes", "No") -> Yes
A84: Jaws 3-D | B84: PG | C84: Adventure | D84: 1983 | E84: July 22, 1983 (United States) | F84: 3.7 | G84: 41000 | H84: Joe Alves | I84: Peter Benchley | J84: Dennis Quaid | K84: United States | L84: 20500000 | M84: 87987055 | N84: Universal Pictures | O84: 99 | P84: =_xlfn.XLOOKUP(D84,Consumer_Price_Index!A:A,Consumer_Price_Index!B:B) -> 99.6 | Q84: =IF(ISNUMBER(M84), M84*(Consumer_Price_Index!$B$45/(_xlfn.XLOOKUP('Working Data'!D342,Consumer_Price_Index!A:A,Consumer_Price_Index!B:B))), "Missing") -> 1.0484809e+08 | R84: =IF(AND(ISNUMBER(L84), L84>0, ISNUMBER(M84), M84>0), "Yes", "No") -> Yes
A85: Joy of Sex | B85: R | C85: Comedy | D85: 1984 | E85: August 3, 1984 (United States) | F85: 3.7 | G85: 705 | H85: Martha Coolidge | I85: Kathleen Rowell | J85: Cameron Dye | K85: United States | M85: 4463841 | N85: Paramount Pictures | O85: 93 | P85: =_xlfn.XLOOKUP(D85,Consumer_Price_Index!A:A,Consumer_Price_Index!B:B) -> 103.9 | Q85: =IF(ISNUMBER(M85), M85*(Consumer_Price_Index!$B$45/(_xlfn.XLOOKUP('Working Data'!D564,Consumer_Price_Index!A:A,Consumer_Price_Index!B:B))), "Missing") -> 6340943.4 | R85: =IF(AND(ISNUMBER(L85), L85>0, ISNUMBER(M85), M85>0), "Yes", "No") -> No
A86: Meatballs Part II | B86: PG | C86: Comedy | D86: 1984 | E86: July 27, 1984 (United States) | F86: 3.7 | G86: 2300 | H86: Ken Wiederhorn | I86: Martin Kitrosser | J86: Richard Mulligan | K86: United States | M86: 5410972 | N86: TriStar Pictures | O86: 87 | P86: =_xlfn.XLOOKUP(D86,Consumer_Price_Index!A:A,Consumer_Price_Index!B:B) -> 103.9 | Q86: =IF(ISNUMBER(M86), M86*(Consumer_Price_Index!$B$45/(_xlfn.XLOOKUP('Working Data'!D580,Consumer_Price_Index!A:A,Consumer_Price_Index!B:B))), "Missing") -> 8442002.9 | R86: =IF(AND(ISNUMBER(L86), L86>0, ISNUMBER(M86), M86>0), "Yes", "No") -> No
A87: Megaforce | B87: PG | C87: Action | D87: 1982 | E87: June 25, 1982 (United States) | F87: 3.7 | G87: 3400 | H87: Hal Needham | I87: Bob Kachler | J87: Barry Bostwick | K87: Hong Kong | L87: 20000000 | M87: 5675599 | N87: Golden Harvest Company | O87: 99 | P87: =_xlfn.XLOOKUP(D87,Consumer_Price_Index!A:A,Consumer_Price_Index!B:B) -> 96.5 | Q87: =IF(ISNUMBER(M87), M87*(Consumer_Price_Index!$B$45/(_xlfn.XLOOKUP('Working Data'!D258,Consumer_Price_Index!A:A,Consumer_Price_Index!B:B))), "Missing") -> 13946411 | R87: =IF(AND(ISNUMBER(L87), L87>0, ISNUMBER(M87), M87>0), "Yes", "No") -> Yes
A88: Mortal Kombat: Annihilation | B88: PG-13 | C88: Action | D88: 1997 | E88: November 21, 1997 (United States) | F88: 3.7 | G88: 51000 | H88: John R. Leonetti | I88: Ed Boon | J88: Robin Shou | K88: United States | L88: 30000000 | M88: 51376861 | N88: New Line Cinema | O88: 95 | P88: =_xlfn.XLOOKUP(D88,Consumer_Price_Index!A:A,Consumer_Price_Index!B:B) -> 160.5 | Q88: =IF(ISNUMBER(M88), M88*(Consumer_Price_Index!$B$45/(_xlfn.XLOOKUP('Working Data'!D3113,Consumer_Price_Index!A:A,Consumer_Price_Index!B:B))), "Missing") -> 63869970 | R88: =IF(AND(ISNUMBER(L88), L88>0, ISNUMBER(M88), M88>0), "Yes", "No") -> Yes
A89: Piranha 3DD | B89: R | C89: Comedy | D89: 2012 | E89: July 14, 2012 (Japan) | F89: 3.7 | G89: 41000 | H89: John Gulager | I89: Patrick Melton | J89: Danielle Panabaker | K89: United States | L89: 5000000 | M89: 8518634 | N89: Dimension Films | O89: 83 | P89: =_xlfn.XLOOKUP(D89,Consumer_Price_Index!A:A,Consumer_Price_Index!B:B) -> 229.6 | Q89: =IF(ISNUMBER(M89), M89*(Consumer_Price_Index!$B$45/(_xlfn.XLOOKUP('Working Data'!D6088,Consumer_Price_Index!A:A,Consumer_Price_Index!B:B))), "Missing") -> 19859432 | R89: =IF(AND(ISNUMBER(L89), L89>0, ISNUMBER(M89), M89>0), "Yes", "No") -> Yes
A90: Street Fighter: The Legend of Chun-Li | B90: PG-13 | C90: Action | D90: 2009 | E90: February 27, 2009 (United States) | F90: 3.7 | G90: 23000 | H90: Andrzej Bartkowiak | I90: Justin Marks | J90: Kristin Kreuk | K90: Canada | L90: 18000000 | M90: 12764201 | N90: Hyde Park Entertainment | O90: 96 | P90: =_xlfn.XLOOKUP(D90,Consumer_Price_Index!A:A,Consumer_Price_Index!B:B) -> 214.5 | Q90: =IF(ISNUMBER(M90), M90*(Consumer_Price_Index!$B$45/(_xlfn.XLOOKUP('Working Data'!D5635,Consumer_Price_Index!A:A,Consumer_Price_Index!B:B))), "Missing") -> 21960768 | R90: =IF(AND(ISNUMBER(L90), L90>0, ISNUMBER(M90), M90>0), "Yes", "No") -> Yes
A91: Superman IV: The Quest for Peace | B91: PG | C91: Action | D91: 1987 | E91: July 24, 1987 (United States) | F91: 3.7 | G91: 44000 | H91: Sidney J. Furie | I91: Jerry Siegel | J91: Christopher Reeve | K91: United Kingdom | L91: 17000000 | M91: 15681020 | N91: Cannon Films | O91: 90 | P91: =_xlfn.XLOOKUP(D91,Consumer_Price_Index!A:A,Consumer_Price_Index!B:B) -> 113.6 | Q91: =IF(ISNUMBER(M91), M91*(Consumer_Price_Index!$B$45/(_xlfn.XLOOKUP('Working Data'!D1077,Consumer_Price_Index!A:A,Consumer_Price_Index!B:B))), "Missing") -> 23700431 | R91: =IF(AND(ISNUMBER(L91), L91>0, ISNUMBER(M91), M91>0), "Yes", "No") -> Yes
A92: The Adventures of Sharkboy and Lavagirl 3-D | B92: PG | C92: Action | D92: 2004 | E92: June 10, 2005 (United States) | F92: 3.7 | G92: 35000 | H92: Robert Rodriguez | I92: Robert Rodriguez | J92: Cayden Boyd | K92: United States | L92: 50000000 | M92: 71992655 | N92: Dimension Films | O92: 93 | P92: =_xlfn.XLOOKUP(D92,Consumer_Price_Index!A:A,Consumer_Price_Index!B:B) -> 188.9 | Q92: =IF(ISNUMBER(M92), M92*(Consumer_Price_Index!$B$45/(_xlfn.XLOOKUP('Working Data'!D4537,Consumer_Price_Index!A:A,Consumer_Price_Index!B:B))), "Missing") -> 1.273877e+08 | R92: =IF(AND(ISNUMBER(L92), L92>0, ISNUMBER(M92), M92>0), "Yes", "No") -> Yes
A93: The Flintstones in Viva Rock Vegas | B93: PG | C93: Comedy | D93: 2000 | E93: April 28, 2000 (United States) | F93: 3.7 | G93: 22000 | H93: Brian Levant | I93: William Hanna | J93: Mark Addy | K93: United States | L93: 83000000 | M93: 59468275 | N93: Universal Pictures | O93: 90 | P93: =_xlfn.XLOOKUP(D93,Consumer_Price_Index!A:A,Consumer_Price_Index!B:B) -> 172.2 | Q93: =IF(ISNUMBER(M93), M93*(Consumer_Price_Index!$B$45/(_xlfn.XLOOKUP('Working Data'!D3720,Consumer_Price_Index!A:A,Consumer_Price_Index!B:B))), "Missing") -> 1.3863798e+08 | R93: =IF(AND(ISNUMBER(L93), L93>0, ISNUMBER(M93), M93>0), "Yes", "No") -> Yes
A94: The Fog | B94: PG-13 | C94: Horror | D94: 2005 | E94: October 14, 2005 (United States) | F94: 3.7 | G94: 35000 | H94: Rupert Wainwright | I94: Cooper Layne | J94: Tom Welling | K94: United States | L94: 18000000 | M94: 46201432 | N94: Revolution Studios | O94: 100 | P94: =_xlfn.XLOOKUP(D94,Consumer_Price_Index!A:A,Consumer_Price_Index!B:B) -> 195.3 | Q94: =IF(ISNUMBER(M94), M94*(Consumer_Price_Index!$B$45/(_xlfn.XLOOKUP('Working Data'!D4793,Consumer_Price_Index!A:A,Consumer_Price_Index!B:B))), "Missing") -> 81751314 | R94: =IF(AND(ISNUMBER(L94), L94>0, ISNUMBER(M94), M94>0), "Yes", "No") -> Yes
A95: The Room | B95: R | C95: Drama | D95: 2003 | E95: June 27, 2003 (Italy) | F95: 3.7 | G95: 84000 | H95: Tommy Wiseau | I95: Tommy Wiseau | J95: Tommy Wiseau | K95: United States | L95: 6000000 | M95: 4988181 | N95: Wiseau-Films | O95: 99 | P95: =_xlfn.XLOOKUP(D95,Consumer_Price_Index!A:A,Consumer_Price_Index!B:B) -> 184 | Q95: =IF(ISNUMBER(M95), M95*(Consumer_Price_Index!$B$45/(_xlfn.XLOOKUP('Working Data'!D4274,Consumer_Price_Index!A:A,Consumer_Price_Index!B:B))), "Missing") -> 6619768.1 | R95: =IF(AND(ISNUMBER(L95), L95>0, ISNUMBER(M95), M95>0), "Yes", "No") -> Yes
A96: The Wicker Man | B96: PG-13 | C96: Horror | D96: 2006 | E96: September 1, 2006 (United States) | F96: 3.7 | G96: 65000 | H96: Neil LaBute | I96: Neil LaBute | J96: Nicolas Cage | K96: United States | L96: 40000000 | M96: 38805380 | N96: Warner Bros. | O96: 102 | P96: =_xlfn.XLOOKUP(D96,Consumer_Price_Index!A:A,Consumer_Price_Index!B:B) -> 201.6 | Q96: =IF(ISNUMBER(M96), M96*(Consumer_Price_Index!$B$45/(_xlfn.XLOOKUP('Working Data'!D4953,Consumer_Price_Index!A:A,Consumer_Price_Index!B:B))), "Missing") -> 81826985 | R96: =IF(AND(ISNUMBER(L96), L96>0, ISNUMBER(M96), M96>0), "Yes", "No") -> Yes
A97: Turbo: A Power Rangers Movie | B97: PG | C97: Action | D97: 1997 | E97: March 28, 1997 (United States) | F97: 3.7 | G97: 8300 | H97: Shuki Levy | I97: Shuki Levy | J97: Jason David Frank | K97: United States | L97: 8000000 | M97: 9615840 | N97: Twentieth Century Fox | O97: 99 | P97: =_xlfn.XLOOKUP(D97,Consumer_Price_Index!A:A,Consumer_Price_Index!B:B) -> 160.5 | Q97: =IF(ISNUMBER(M97), M97*(Consumer_Price_Index!$B$45/(_xlfn.XLOOKUP('Working Data'!D3161,Consumer_Price_Index!A:A,Consumer_Price_Index!B:B))), "Missing") -> 25791782 | R97: =IF(AND(ISNUMBER(L97), L97>0, ISNUMBER(M97), M97>0), "Yes", "No") -> Yes
A98: Wired | B98: R | C98: Biography | D98: 1989 | E98: August 25, 1989 (United States) | F98: 3.7 | G98: 790 | H98: Larry Peerce | I98: Bob Woodward | J98: Michael Chiklis | K98: United States | M98: 1089000 | N98: FM Entertainment | O98: 112 | P98: =_xlfn.XLOOKUP(D98,Consumer_Price_Index!A:A,Consumer_Price_Index!B:B) -> 124 | Q98: =IF(ISNUMBER(M98), M98*(Consumer_Price_Index!$B$45/(_xlfn.XLOOKUP('Working Data'!D1595,Consumer_Price_Index!A:A,Consumer_Price_Index!B:B))), "Missing") -> 1756581.8 | R98: =IF(AND(ISNUMBER(L98), L98>0, ISNUMBER(M98), M98>0), "Yes", "No") -> No
A99: Batman & Robin | B99: PG-13 | C99: Action | D99: 1997 | E99: June 20, 1997 (United States) | F99: 3.8 | G99: 238000 | H99: Joel Schumacher | I99: Bob Kane | J99: Arnold Schwarzenegger | K99: United States | L99: 125000000 | M99: 238235719 | N99: Warner Bros. | O99: 125 | P99: =_xlfn.XLOOKUP(D99,Consumer_Price_Index!A:A,Consumer_Price_Index!B:B) -> 160.5 | Q99: =IF(ISNUMBER(M99), M99*(Consumer_Price_Index!$B$45/(_xlfn.XLOOKUP('Working Data'!D3062,Consumer_Price_Index!A:A,Consumer_Price_Index!B:B))), "Missing") -> 7.5223237e+08 | R99: =IF(AND(ISNUMBER(L99), L99>0, ISNUMBER(M99), M99>0), "Yes", "No") -> Yes
A100: Best Defense | B100: R | C100: Comedy | D100: 1984 | E100: July 20, 1984 (United States) | F100: 3.8 | G100: 5600 | H100: Willard Huyck | I100: Robert Grossbach | J100: Dudley Moore | K100: United States | L100: 18000000 | M100: 19265302 | N100: Cinema Group Ventures | O100: 94 | P100: =_xlfn.XLOOKUP(D100,Consumer_Price_Index!A:A,Consumer_Price_Index!B:B) -> 103.9 | Q100: =IF(ISNUMBER(M100), M100*(Consumer_Price_Index!$B$45/(_xlfn.XLOOKUP('Working Data'!D595,Consumer_Price_Index!A:A,Consumer_Price_Index!B:B))), "Missing") -> 27366608 | R100: =IF(AND(ISNUMBER(L100), L100>0, ISNUMBER(M100), M100>0), "Yes", "No") -> Yes
...

Sheet pivottable_genre
A1: Valid movie | B1: Yes
A3: Row Labels | B3: Average of Gross relative to budget
A4: Action | B4: 2.8727601
A5: Adventure | B5: 2.8997264
A6: Animation | B6: 3.6833103
A7: Biography | B7: 2.4134502
A8: Comedy | B8: 2.5948028
A9: Crime | B9: 2.218839
A10: Drama | B10: 2.5972081
A11: Family | B11: 10.143436
A12: Fantasy | B12: 2.3279211
A13: Horror | B13: 4.2219441
A14: Mystery | B14: 3.6982681
A15: Romance | B15: 1.3966465
... A19: Grand Total | B19: 2.8661203

Sheet pivottable_rating
A1: Valid movie | B1: Yes
A3: Row Labels | B3: Average of Gross relative to budget
A4: G | B4: 3.5504056
A5: NC-17 | B5: 1.5843237
A6: PG | B6: 3.1217287
A7: PG-13 | B7: 3.0216556
A8: R | B8: 2.40136
A9: Grand Total | B9: 2.864802

Sheet pivottable_score
A2: Valid movie | B2: Yes
A4: Row Labels | B4: Average of Gross relative to budget
A5: 8-9 | B5: 5.9867212
A6: 9-10 | B6: 4.9275759
A7: 7-8 | B7: 3.7524221
A8: 6-7 | B8: 2.5834207
A9: 5-6 | B9: 1.9381276
A10: 4-5 | B10: 1.7977551
A11: 3-4 | B11: 1.2591825
A12: 1-2 | B12: 1.1066367
A13: 2-3 | B13: 0.93170756
A14: Grand Total | B14: 2.8661203

Sheet Inflation_adjusted_pivot
A3: Row Labels | B3: Sum of Gross Revenue in 2023 Dollars
A4: 1980 | B4: 4.3784903e+09
A5: 1981 | B5: 5.155092e+09
A6: 1982 | B6: 6.2978915e+09
A7: 1983 | B7: 5.4801162e+09
A8: 1984 | B8: 8.1056768e+09
A9: 1985 | B9: 7.7307778e+09
A10: 1986 | B10: 6.7159311e+09
A11: 1987 | B11: 8.3863461e+09
A12: 1988 | B12: 9.9325604e+09
A13: 1989 | B13: 1.1183829e+10
A14: 1990 | B14: 1.2734153e+10
A15: 1991 | B15: 1.1184934e+10
... A44: 2020 | B44: 5.3195422e+09
A45: Grand Total | B45: 1.1026885e+12

Sheet Pivot_Chart
A3: Row Labels | B3: Sum of gross
A4: 1980 | B4: 2483666964
A5: 1981 | B5: 2520064889
A6: 1982 | B6: 3187580517
A7: 1983 | B7: 2750004626
A8: 1984 | B8: 3533092196
A9: 1985 | B9: 3691509283
A10: 1986 | B10: 3647511836
A11: 1987 | B11: 4033434255
A12: 1988 | B12: 4840385631
A13: 1989 | B13: 6087250779
A14: 1990 | B14: 6804235860
A15: 1991 | B15: 6254770668
... A44: 2020 | B44: 2848298792
A45: Grand Total | B45: 587105546272

Sheet Consumer_Price_Index
A1: Year | B1: Annual Average CPI (-U) | C1: Annual Percent Change (rate of inflation)
A2: 1980 | B2: 82.4 | C2: 0.135
A3: 1981 | B3: 90.9 | C3: 0.103
A4: 1982 | B4: 96.5 | C4: 0.061
A5: 1983 | B5: 99.6 | C5: 0.032
A6: 1984 | B6: 103.9 | C6: 0.043
A7: 1985 | B7: 107.6 | C7: 0.035
A8: 1986 | B8: 109.6 | C8: 0.019
A9: 1987 | B9: 113.6 | C9: 0.037
A10: 1988 | B10: 118.3 | C10: 0.041
A11: 1989 | B11: 124 | C11: 0.048
A12: 1990 | B12: 130.7 | C12: 0.054
A13: 1991 | B13: 136.2 | C13: 0.042
... A47: 2025 | B47: 322.3 | C47: 0.027
